{"html_attributions": [], "result": {"address_components": [{"long_name": "97", "short_name": "97", "types": ["street_number"]}, {"long_name": "Velyka Vasylkivska Street", "short_name": "Velyka Vasylkivska St", "types": ["route"]}, {"long_name": "Pechers'kyi district", "short_name": "Pechers'kyi district", "types": ["sublocality_level_1", "sublocality", "political"]}, {"long_name": "Kyiv", "short_name": "Kyiv", "types": ["locality", "political"]}, {"long_name": "Kyiv City", "short_name": "Kyiv City", "types": ["administrative_area_level_2", "political"]}, {"long_name": "Kyiv", "short_name": "Kyiv", "types": ["administrative_area_level_1", "political"]}, {"long_name": "Ukraine", "short_name": "UA", "types": ["country", "political"]}, {"long_name": "03150", "short_name": "03150", "types": ["postal_code"]}], "adr_address": "<span class=\"street-address\">Velyka Vasylkivska St, 97</span>, <span class=\"locality\">Kyiv</span>, <span class=\"country-name\">Ukraine</span>, <span class=\"postal-code\">03150</span>", "business_status": "OPERATIONAL", "curbside_pickup": true, "current_opening_hours": {"open_now": false, "periods": [{"close": {"date": "2024-03-18", "day": 1, "time": "2200"}, "open": {"date": "2024-03-18", "day": 1, "time": "1200"}}, {"close": {"date": "2024-03-19", "day": 2, "time": "2200"}, "open": {"date": "2024-03-19", "day": 2, "time": "1200"}}, {"close": {"date": "2024-03-20", "day": 3, "time": "2200"}, "open": {"date": "2024-03-20", "day": 3, "time": "1200"}}, {"close": {"date": "2024-03-21", "day": 4, "time": "2200"}, "open": {"date": "2024-03-21", "day": 4, "time": "1200"}}, {"close": {"date": "2024-03-22", "day": 5, "time": "2300"}, "open": {"date": "2024-03-22", "day": 5, "time": "1200"}}, {"close": {"date": "2024-03-23", "day": 6, "time": "1700"}, "open": {"date": "2024-03-23", "day": 6, "time": "0900"}}], "weekday_text": ["Monday: 12:00 – 10:00 PM", "Tuesday: 12:00 – 10:00 PM", "Wednesday: 12:00 – 10:00 PM", "Thursday: 12:00 – 10:00 PM", "Friday: 12:00 – 11:00 PM", "Saturday: 9:00 AM – 5:00 PM", "Sunday: Closed"]}, "delivery": true, "dine_in": true, "formatted_address": "Velyka Vasylkivska St, 97, Kyiv, Ukraine, 03150", "formatted_phone_number": "099 214 7561", "geometry": {"location": {"lat": 50.42401160000001, "lng": 30.5189768}, "viewport": {"northeast": {"lat": 50.4253140302915, "lng": 30.52014888029149}, "southwest": {"lat": 50.4226160697085, "lng": 30.51745091970849}}}, "icon": "https://maps.gstatic.com/mapfiles/place_api/icons/v1/png_71/bar-71.png", "icon_background_color": "#FF9E67", "icon_mask_base_uri": "https://maps.gstatic.com/mapfiles/place_api/icons/v2/bar_pinlet", "international_phone_number": "+380 99 214 7561", "name": "Copper Pub", "opening_hours": {"open_now": false, "periods": [{"close": {"day": 1, "time": "2200"}, "open": {"day": 1, "time": "1200"}}, {"close": {"day": 2, "time": "2200"}, "open": {"day": 2, "time": "1200"}}, {"close": {"day": 3, "time": "2200"}, "open": {"day": 3, "time": "1200"}}, {"close": {"day": 4, "time": "2200"}, "open": {"day": 4, "time": "1200"}}, {"close": {"day": 5, "time": "2300"}, "open": {"day": 5, "time": "1200"}}, {"close": {"day": 6, "time": "1700"}, "open": {"day": 6, "time": "0900"}}], "weekday_text": ["Monday: 12:00 – 10:00 PM", "Tuesday: 12:00 – 10:00 PM", "Wednesday: 12:00 – 10:00 PM", "Thursday: 12:00 – 10:00 PM", "Friday: 12:00 – 11:00 PM", "Saturday: 9:00 AM – 5:00 PM", "Sunday: Closed"]}, "photos": [{"height": 1324, "html_attributions": ["<a href=\"https://maps.google.com/maps/contrib/114080424912484293578\">Copper Pub</a>"], "photo_reference": "ATplDJaT8-eWK7s9hhOSQVxLRbonZpm9KZxYN44kZUPiQj3Ow-sU2G5em6R6IsflcnjoowV_M9EEq9FJzZUDpTu2XXHFsI7sK0Kvm4E8K7CSDo_cPeq8M16Q4zZryqJCg0WAvLtvVzJGh9oCtcRfEHu1B6twOb3YnggrjyJLof5EDULIjkNR", "width": 2352}, {"height": 2268, "html_attributions": ["<a href=\"https://maps.google.com/maps/contrib/106585497082664084649\">Oleh Romanenko</a>"], "photo_reference": "ATplDJbkTQTQsQaJgABAbpDuVnAhm83YLZNB6WZca9wKFdjPLUY2ug3Qjf3rdOHoaInQNxJPfCxIBpOB3tiELpAHeOp3AYb0mQo6VDv-AFEF0S9NxPtMvMdhZ8ayQbNEqxrL-LkKAL8QcR0RIwDmmkv4MLCf-2zPlQVLVROyMXRKyUib4CvH", "width": 4032}, {"height": 4032, "html_attributions": ["<a href=\"https://maps.google.com/maps/contrib/108700790977814099907\">Алёнка Рычкова</a>"], "photo_reference": "ATplDJbUj2AHyxOWVi_rI5Jca7cEg-u8ozaNLshnXRn5Z9A349fjdkBwp8hRpNV9sjWk6z-sX8chfakdQJTGoy1mn7ypv5PsrfnlLTaPEZNgEZdgyUh9kdQP-njJY3TxjORBGhj3xbGZEhxgEhDkHqcJwMZWkGIi1icfWBcL4IKoVoLT_SuH", "width": 3024}, {"height": 4640, "html_attributions": ["<a href=\"https://maps.google.com/maps/contrib/106843193389007227305\">Олександр Мартинюк</a>"], "photo_reference": "ATplDJZv2t6HpyOQj3Ij54XzW5j3qCBuNLttcsJoou22rg01t2S4mt3cDK53Q-7XwhCvhdPSUbBIjZjTqBLhHjP-G7GxuadryZzPkHMXqeqmmVVvdIsPPQ8HN7V_C3xX6tkVJVFnbuWeOWH3H1ivS1ewCio8uaVmPC0bW2_GDzaiGYCkgeae", "width": 3472}, {"height": 4032, "html_attributions": ["<a href=\"https://maps.google.com/maps/contrib/112330060539147061653\">Iryna Polat</a>"], "photo_reference": "ATplDJZvaD0s9ui0JlkO4OODSwnQNrLjvBlr_mPqLo24s2ku3EMs8St_qFmv3FbXaS-nsx3FzAxkf5QPetc7nPpm5HFJMPjCcYFxcXlACzWbOJ_zuDr2ohieY8XU8wM8dmVQx_VKxXBvGXnPGub0FGl2sfhB-RIteW0z0mudvGO4qJaWM4Jl", "width": 3024}, {"height": 1042, "html_attributions": ["<a href=\"https://maps.google.com/maps/contrib/114080424912484293578\">Copper Pub</a>"], "photo_reference": "ATplDJZChRgmSvQf1fIZDIf1cephZhuyq5C7TpHg5BM68fPId14V52bXTXLsifXEnq-XQUgYvrJwTFc-64OV-yW0Qu8lKPMpOcMsWB604AljAL8aCn2ASrOpt9XNw_P44hs58yWpk2jXGXL2Gtzk4_3x8STryyZl8DWANBa4D-UUHiBWxi-S", "width": 1852}, {"height": 4000, "html_attributions": ["<a href=\"https://maps.google.com/maps/contrib/107915959696080233875\">Любовь Пограничная</a>"], "photo_reference": "ATplDJYRDFnz4SjUNX8qYZOkoUogu_o4Gd4VimKYwWPSVffuuCp5_l6CdH0LNMwVWPQMYCaQ0HcJF5Uh7QhMxI-gC3eyZmSTMx3kOmslar3nbrxpITFLtaubdhkiApp-5rw7c_KwLIwMsEmttMyGxswI6arofP8W1yVhtT05GiqSFwA3nuHM", "width": 2250}, {"height": 4032, "html_attributions": ["<a href=\"https://maps.google.com/maps/contrib/115748919908862609795\">Dominik Nieder</a>"], "photo_reference": "ATplDJYe37FdtsV-WD3jWkKE8GCYltrhbSeMZK7pqlWUy0Nyy-NRU6_p3MzNhngsEy9rmFXSvwtiG9hEsp0QD_AfmE3rIggXYk-9q9c5ktQ0oy3dpUCSTLOX73kyCNxDOQGdokCA0s5fnWb7UKW8AVo3YkX51Kl0RPcaSOlMCDjfJASU5ZQ", "width": 3024}, {"height": 3973, "html_attributions": ["<a href=\"https://maps.google.com/maps/contrib/116732054157669461830\">Oleg Butenko</a>"], "photo_reference": "ATplDJYlpBois7QeB6m-BCXtqFBnxxiWRyNRKGlEuMsG5O-l9UcURN8gfalE3uFXxUUnN6MZD7o9OPFNkNhtTaZNG_vPJrX4T3mWzDNJRuiMAgSlzxnWGiGgB_DUrNtYmOQ6feWMHLvK3PqURaFPehieA7_VH7701nlcpJ_6j3Tj2L8x8vXR", "width": 3973}, {"height": 3370, "html_attributions": ["<a href=\"https://maps.google.com/maps/contrib/114080424912484293578\">Copper Pub</a>"], "photo_reference": "ATplDJZhJWaWt5YEh-_1iSaPy3YRTF2L4HEKfzOQP5J6-ExxbtOODqqr0D30-lY3R3xRLLzL_OYY_mpNwH5xotR5Rt6kw3Mn1dvqI5rpQs2wHcZmZm1uLa2mLIKwomtvy0vK6Er_FcZXr-vctu9MHXpBcJ2UG_TLDePKqJeDX2ANHMpxeC-p", "width": 4683}], "place_id": "ChIJQcUsPRnP1EARJJkmuNWJI2U", "plus_code": {"compound_code": "CGF9+JH Kyiv, Kyiv city, Ukraine", "global_code": "9G2GCGF9+JH"}, "price_level": 2, "rating": 4.4, "reservable": true, "reviews": [{"author_name": "Alina Demidchenko", "author_url": "https://www.google.com/maps/contrib/114172716777716027281/reviews", "language": "en", "original_language": "en", "profile_photo_url": "https://lh3.googleusercontent.com/a-/ALV-UjUZ6qk8e6AdxHVvmk3G15x0QXrpFtx8FrPyjnEEGCiMhQXj=s128-c0x00000000-cc-rp-mo-ba5", "rating": 4, "relative_time_description": "4 years ago", "text": "A nice place with good prices. Loved all the dog items in the design) We tasted a lot of dishes and they were okay, not bad but not amazing either. It was rather crowded and we had to wait for our orders longer than desired. There are a lot of good special  offers on drinks.", "time": 1553233920, "translated": false}, {"author_name": "Dmytro Buldakov", "author_url": "https://www.google.com/maps/contrib/109156407896911978658/reviews", "language": "en", "original_language": "en", "profile_photo_url": "https://lh3.googleusercontent.com/a-/ALV-UjV-ypXvys3r0oHv8ajLLyZHk8qjf6C8KewP5evclYn6FZKq=s128-c0x00000000-cc-rp-mo-ba7", "rating": 4, "relative_time_description": "3 years ago", "text": "Appearance is nice, so that the service is.\n\nSelection of beer is very limited and neither of beer we had on tap were fresh. The beer was not actually spoiled yet, but it already tasted more acidic than it should. We had Grimbergen blonde and ambree, btw.\n\nFood was good. We had grilled vegetables and a burger.", "time": 1609855694, "translated": false}, {"author_name": "Yevhen Logosha", "author_url": "https://www.google.com/maps/contrib/100721115015639412415/reviews", "language": "en", "original_language": "en", "profile_photo_url": "https://lh3.googleusercontent.com/a-/ALV-UjX7PZZKuvmdwn0G3XBkaFStfIE4byJRzNWznsU8DYM3gg=s128-c0x00000000-cc-rp-mo-ba3", "rating": 5, "relative_time_description": "4 years ago", "text": "One of the best places for pint of Guinness and Heineken in Kyiv. Average prices and food, yet nothing too bad. Friendly staff and pub atmosphere. Has small outside sitting area for a quick guilty pleasure.", "time": 1572775471, "translated": false}, {"author_name": "Andrew Mish", "author_url": "https://www.google.com/maps/contrib/100481227313456274304/reviews", "language": "en", "original_language": "en", "profile_photo_url": "https://lh3.googleusercontent.com/a/ACg8ocKuR40b_vPIyCZKQA_OJkdPleHGpZCx7ZMlDeiYgw4M=s128-c0x00000000-cc-rp-mo-ba4", "rating": 3, "relative_time_description": "4 years ago", "text": "Dropped by this place by accident - we were walking by and saw it. Pretty vibrant interior with good decor.\n\nThe food was good, we got chicken wings and pickles - decent prices.\n\nHowever, the crowd was on the rowdy side. The table next to us was quite drunk - the guys were yelling and picking fights with the patrons. Another lady from a different table came up to the manager and started to pick a fight with him. When I asked the bartender if this was a normal crowd, he said, “yes it is.” We probably won’t come back here because of that.", "time": 1579383240, "translated": false}, {"author_name": "Anton Gulyi", "author_url": "https://www.google.com/maps/contrib/100464785258570943905/reviews", "language": "en", "original_language": "en", "profile_photo_url": "https://lh3.googleusercontent.com/a-/ALV-UjWqb_uyt43bOdQ6sT-KDQIRJKjkGW2y0mtMIdN0Ew8VkEs=s128-c0x00000000-cc-rp-mo-ba4", "rating": 5, "relative_time_description": "4 years ago", "text": "Really nice, inexpensive place to get some beer and pub food, plus they have several healthy choices on the menu. Staff is very welcoming and attentive.", "time": 1560691885, "translated": false}], "serves_beer": true, "serves_breakfast": true, "serves_dinner": true, "serves_lunch": true, "serves_wine": true, "takeout": true, "types": ["bar", "point_of_interest", "establishment"], "url": "https://maps.google.com/?cid=7287820173026171172", "user_ratings_total": 1114, "utc_offset": 120, "vicinity": "Velyka Vasylkivska Street, 97, Kyiv"}, "status": "OK"}