{"html_attributions": [], "result": {"address_components": [{"long_name": "18", "short_name": "18", "types": ["street_number"]}, {"long_name": "Yelyzavety Chavdar Street", "short_name": "Yelyzavety Chavdar St", "types": ["route"]}, {"long_name": "Darnyts'kyi District", "short_name": "Darnyts'kyi District", "types": ["sublocality_level_1", "sublocality", "political"]}, {"long_name": "Kyiv", "short_name": "Kyiv", "types": ["locality", "political"]}, {"long_name": "Kyiv City", "short_name": "Kyiv City", "types": ["administrative_area_level_2", "political"]}, {"long_name": "Kyiv", "short_name": "Kyiv", "types": ["administrative_area_level_1", "political"]}, {"long_name": "Ukraine", "short_name": "UA", "types": ["country", "political"]}, {"long_name": "02068", "short_name": "02068", "types": ["postal_code"]}], "adr_address": "<span class=\"street-address\">Yelyzavety Chavdar St, 18</span>, <span class=\"locality\">Kyiv</span>, <span class=\"country-name\">Ukraine</span>, <span class=\"postal-code\">02068</span>", "business_status": "OPERATIONAL", "curbside_pickup": true, "current_opening_hours": {"open_now": true, "periods": [{"close": {"date": "2024-03-17", "day": 0, "time": "2200"}, "open": {"date": "2024-03-17", "day": 0, "time": "1000"}}, {"close": {"date": "2024-03-18", "day": 1, "time": "2200"}, "open": {"date": "2024-03-18", "day": 1, "time": "1000"}}, {"close": {"date": "2024-03-19", "day": 2, "time": "2200"}, "open": {"date": "2024-03-19", "day": 2, "time": "1000"}}, {"close": {"date": "2024-03-20", "day": 3, "time": "2200"}, "open": {"date": "2024-03-20", "day": 3, "time": "1000"}}, {"close": {"date": "2024-03-21", "day": 4, "time": "2200"}, "open": {"date": "2024-03-21", "day": 4, "time": "1000"}}, {"close": {"date": "2024-03-22", "day": 5, "time": "2200"}, "open": {"date": "2024-03-22", "day": 5, "time": "1000"}}, {"close": {"date": "2024-03-23", "day": 6, "time": "2200"}, "open": {"date": "2024-03-23", "day": 6, "time": "1000"}}], "weekday_text": ["Monday: 10:00 AM – 10:00 PM", "Tuesday: 10:00 AM – 10:00 PM", "Wednesday: 10:00 AM – 10:00 PM", "Thursday: 10:00 AM – 10:00 PM", "Friday: 10:00 AM – 10:00 PM", "Saturday: 10:00 AM – 10:00 PM", "Sunday: 10:00 AM – 10:00 PM"]}, "delivery": true, "formatted_address": "Yelyzavety Chavdar St, 18, Kyiv, Ukraine, 02068", "formatted_phone_number": "0800 332 220", "geometry": {"location": {"lat": 50.3895345, "lng": 30.62439669999999}, "viewport": {"northeast": {"lat": 50.39118518029149, "lng": 30.6259997302915}, "southwest": {"lat": 50.3884872197085, "lng": 30.6233017697085}}}, "icon": "https://maps.gstatic.com/mapfiles/place_api/icons/v1/png_71/restaurant-71.png", "icon_background_color": "#FF9E67", "icon_mask_base_uri": "https://maps.gstatic.com/mapfiles/place_api/icons/v2/restaurant_pinlet", "international_phone_number": "+380 800 332 220", "name": "Sushi Point", "opening_hours": {"open_now": true, "periods": [{"close": {"day": 0, "time": "2200"}, "open": {"day": 0, "time": "1000"}}, {"close": {"day": 1, "time": "2200"}, "open": {"day": 1, "time": "1000"}}, {"close": {"day": 2, "time": "2200"}, "open": {"day": 2, "time": "1000"}}, {"close": {"day": 3, "time": "2200"}, "open": {"day": 3, "time": "1000"}}, {"close": {"day": 4, "time": "2200"}, "open": {"day": 4, "time": "1000"}}, {"close": {"day": 5, "time": "2200"}, "open": {"day": 5, "time": "1000"}}, {"close": {"day": 6, "time": "2200"}, "open": {"day": 6, "time": "1000"}}], "weekday_text": ["Monday: 10:00 AM – 10:00 PM", "Tuesday: 10:00 AM – 10:00 PM", "Wednesday: 10:00 AM – 10:00 PM", "Thursday: 10:00 AM – 10:00 PM", "Friday: 10:00 AM – 10:00 PM", "Saturday: 10:00 AM – 10:00 PM", "Sunday: 10:00 AM – 10:00 PM"]}, "photos": [{"height": 1200, "html_attributions": ["<a href=\"https://maps.google.com/maps/contrib/104412105085525185798\">Sushi Point</a>"], "photo_reference": "ATplDJYXv2-ZRHH4GRBFuVsPHzkfWSO9dksfACVpVC-BF9biUkyfAo04zmXInxNPT_Lr8Sv7iNc1DJU6l1EIUdzpcz-m3WM2wsuu4TAGDDYN0koTtkRSsWZNvOUrXlsscEkZs7NvdJyNN4IMGjv-OAielYTXxTBd6v0qvaMh9z-f4vnSmox5", "width": 1600}, {"height": 3420, "html_attributions": ["<a href=\"https://maps.google.com/maps/contrib/104412105085525185798\">Sushi Point</a>"], "photo_reference": "ATplDJaC4qN80eZb0lM9oueaX2ka5MH-26yii23wVe5t8F4I-7LOskD5X5Lk8gXeXsIXjV9vC9efjmkxPQkUrh4mTUjHvDpXtaxcxEfh0JhdPg61lmT0N3I4k1sNmw2V6-4ajzqoDRck8W6mep-lZQS8SJikvpUTKW_L08HVSuVJYytpK0O_", "width": 2736}, {"height": 3024, "html_attributions": ["<a href=\"https://maps.google.com/maps/contrib/110642286923309673274\">Oleg Podolskiy</a>"], "photo_reference": "ATplDJbgAINiLYlzZwB3_VEeKdTsTwj0i1wvTos4SXWzvTd9ay8etV53jfCdHy508BXugYdimgUdYXnXp2ZMrAv3mMr94aZId7gJEFSymNtMLlwWNcHsby1dWxoz2lDU2c-aW_HGQUCwfbwK8rFVKlMt1WcyLIzbLrEA5oDP9WcCZA71qfw8", "width": 4032}, {"height": 3120, "html_attributions": ["<a href=\"https://maps.google.com/maps/contrib/117774378114817705276\">Юлія Троян</a>"], "photo_reference": "ATplDJakYIISfQ9qW8CESU2KpSYC9xCsJEv1AaEEKB_gn04yNKDdV7KFfiG7DWdio3f8uJJbljcfkO29ushxnAS5Z0MMM93w0DVA7o4JCspQTkEJFSBN14Ib5Y033CkpT1_VHI1b46fpQfWI16mjfwpjjozcRjmVjx_culwrW8tM4eFxu2VJ", "width": 4160}, {"height": 4080, "html_attributions": ["<a href=\"https://maps.google.com/maps/contrib/103519582372457292305\">Дарья Шателюк</a>"], "photo_reference": "ATplDJZxls5XB5QF3Utv-8GrC2fTHy3GvDzB8dEzsLh9NVyN97TecOK02Sfuva5eYHpuzM2U4vAM89EpWM_qELEtEi5DVjsoJbDBqIQlB9Ol6Se0kN68qkn5hoDqXYfwQA25t5hCFFcyxK-f5zkysPjkmX5sT8x20mov5gb6EYd6wQbNxD00", "width": 1836}, {"height": 3420, "html_attributions": ["<a href=\"https://maps.google.com/maps/contrib/104412105085525185798\">Sushi Point</a>"], "photo_reference": "ATplDJbTuvIWS6MB7P-QHP9ogLQML5awvaK18IGErz-gWvvXV4YNw5DJul7P1e7PbSb_0GvxF3gvkF1BfbVqXAhU7odkQvI3z9gD9pL8dl_o_HoupslDqRaT5HUIA4hWLzC368pTBcVsfjMwn55UB1vtSGc81BD3UfWwHomIC4l-BGmXnGJU", "width": 2736}, {"height": 3420, "html_attributions": ["<a href=\"https://maps.google.com/maps/contrib/104412105085525185798\">Sushi Point</a>"], "photo_reference": "ATplDJZarR52fAXrL2VtbS7kXD8KeDE9_b7E1-c3hlNIsODvPFkM6PSSA67YBX_2CJc-eqtAbsL25D9J2EBj203t0LBMbw51W3ZnzfTobxx0gadVPdrjZuwGTpxiyRCT4X8NxF1ikdf1cV0-rvNQvedahyuXSlLCSrPHgK0Kn19qTm_e5rTK", "width": 2736}, {"height": 4000, "html_attributions": ["<a href=\"https://maps.google.com/maps/contrib/104412105085525185798\">Sushi Point</a>"], "photo_reference": "ATplDJY76e0majPqFb2M_VMrxHMwZsp3XNUwgDWXKH6yDuY9fyo_G0y-aPboq67EC_G7DDikNdV66uZQOdu10brDoqafbU-m1BDsvNdYemm-ndWtv3q0NLGtoufIP5rixyNRY1Pdrcn1g2J5L98umodDj4pKWQWA0yULkYX9saQpbj0aAEWF", "width": 6000}, {"height": 6000, "html_attributions": ["<a href=\"https://maps.google.com/maps/contrib/104412105085525185798\">Sushi Point</a>"], "photo_reference": "ATplDJZovP2Vebet0hcppj7Oaw7eMWezd_fyGzZZGOd2lO__ijAsueDHi_Wqtrysr276XjHXMQWSI8GgMmWN0hNAmyDnVDDZx5fBvToK0pMX7xooOo9OewsWehjebZb-JYsIiDy-6M-Wg3zYU4rTeCI_yea1gmq9VF9Pno_z4ck1TMluh4MS", "width": 4000}, {"height": 3024, "html_attributions": ["<a href=\"https://maps.google.com/maps/contrib/110642286923309673274\">Oleg Podolskiy</a>"], "photo_reference": "ATplDJbGhclZqcIQCj01El3rqs9cfJS8IvkjrzQV_48T7JE-dIRpmqFx1j_k7vB9wN0kKCj5VdbHX_wMGfVwsuBy8St-5ZvXSDtg9p75jVR02B8tzYb57NH4rIwP35dIWSki9xJ5tKa9X0M-u_tpNkiBRCmOl8-BsOcwWB4q4Djsc9FT7cBf", "width": 4032}], "place_id": "ChIJw1fb7pjF1EARvA98SNnYT_w", "plus_code": {"compound_code": "9JQF+RQ Kyiv, Kyiv city, Ukraine", "global_code": "9G2G9JQF+RQ"}, "price_level": 2, "rating": 4.1, "reservable": true, "reviews": [{"author_name": "Oleg Podolskiy", "author_url": "https://www.google.com/maps/contrib/110642286923309673274/reviews", "language": "en-US", "original_language": "ru", "profile_photo_url": "https://lh3.googleusercontent.com/a-/ALV-UjXVt696nW2s-OKKFfn_gNAUfLzed09BIVOKBgvJi8Od68M=s128-c0x00000000-cc-rp-mo", "rating": 1, "relative_time_description": "2 months ago", "text": "Once upon a time there was my favorite chain, I haven’t ordered for a year and now I ordered on December 31 for 944 UAH And I was sad) these are the most expensive rolls, I can’t imagine what’s in the others, in response to the photo with criticism they offered a roll as a gift in the next order. I’m deleting the Sushi Point number, thanks to those who worked at the hippodrome in 21-22, it was cool.", "time": 1704032819, "translated": true}, {"author_name": "MG G", "author_url": "https://www.google.com/maps/contrib/107878719308598575138/reviews", "language": "en-US", "original_language": "ru", "profile_photo_url": "https://lh3.googleusercontent.com/a-/ALV-UjU21iz1WWzf18csnJZaidwY9dCcolcUviVJ3zXdrJYzTFJj=s128-c0x00000000-cc-rp-mo", "rating": 2, "relative_time_description": "3 months ago", "text": "I decided to order because I live nearby. There were no great hopes; I understood the risks after looking at the price. Therefore, I missed out on the super offer of 2 sets of rolls for the price of 1, because if they were not tasty, I didn’t want to throw everything away right away. Well, let's just say that the rolls correspond to their price, normal, but strange. I ate half of it and threw it away. I took the tom yam, my thoughts were the following: well, it’s difficult to make soup tasteless? Sushi Point: is it difficult to do in terms of plan? Take your pens and write down how!” Disgusting watery stew with a slight taste of champignons, which only resembles tom yum in color.\nActually, there are no complaints about the guys, price-quality. I won’t order there again, I’d rather pay a little more and get high-quality and tasty food", "time": 1700744075, "translated": true}, {"author_name": "Дарья Шателюк", "author_url": "https://www.google.com/maps/contrib/103519582372457292305/reviews", "language": "en-US", "original_language": "uk", "profile_photo_url": "https://lh3.googleusercontent.com/a-/ALV-UjUgDXYduirmf5STwGJzv379l95JpDepU1Sio0_ELPPqKhez=s128-c0x00000000-cc-rp-mo", "rating": 4, "relative_time_description": "7 months ago", "text": "The rolls are tasty, the service is fast, it is convenient to order in the application, the staff is friendly. A small cozy area where you can sit\nThe only thing that is a little disappointing is that not all rolls keep their shape, some of them sadly float in soy sauce\nBut for your money - Better is hard to find", "time": 1691178561, "translated": true}, {"author_name": "IGOR bistrov", "author_url": "https://www.google.com/maps/contrib/101063254287719564533/reviews", "language": "en-US", "original_language": "ru", "profile_photo_url": "https://lh3.googleusercontent.com/a/ACg8ocJ3duN51fDvhYDAC_LxuqKx2Qp0Zfd1NJaRH6eny5oX=s128-c0x00000000-cc-rp-mo", "rating": 1, "relative_time_description": "a week ago", "text": "03/8/2024, I bought sushi again and was underweight by 90g on 2 packs! I’m buying for the 3rd and last time, before that it was the same story, I call the hotline, send a photo of the weighing and a refund is issued\nQuestion: why spoil the holiday?\nI strongly do not recommend it, competitors do not allow themselves such impudence and, unfortunately, they did not accept orders today due to the large amount of work!", "time": 1709916202, "translated": true}, {"author_name": "Аліна Абраменко", "author_url": "https://www.google.com/maps/contrib/104473215524466432090/reviews", "language": "en-US", "original_language": "uk", "profile_photo_url": "https://lh3.googleusercontent.com/a-/ALV-UjXflCihf_FMvUYSFvg7ggnbguXJgq3jcsV-WyxgomYj3iU=s128-c0x00000000-cc-rp-mo", "rating": 3, "relative_time_description": "4 months ago", "text": "I used to order rolls from Sushi Point before (somewhere a year ago) and everything was always delicious. Then they changed the menu and I stopped ordering. But yesterday I decided to try again to order delivery for my birthday.\n\nOf all the roles, only Philadelphia was generally ok. Yes, the fish does not cover the entire roll, there is not much filling (the avocado was already a bit dark), a lot of sweet rice. But in general, for this price, it is a normal price-quality.\nThe chuka salad was tasty, perhaps if you wish - add a little more sauce so that it is not so dry.\nThere are two roles as a birthday gift. But they went in the trash. It was just terribly tasteless. In principle, rolls with chicken are a strange story for an amateur, but I have come across delicious combinations in deliveries. These roles were terrible(\nSince these were rolls as a gift, it wasn't too bad to throw them away, but then again, why not make them at least edible? 🙁\n\nI decided to try this delivery again and was disappointed, it's a shame that it was.", "time": 1698057350, "translated": true}], "serves_beer": true, "serves_breakfast": true, "serves_dinner": true, "serves_lunch": true, "takeout": true, "types": ["meal_takeaway", "cafe", "restaurant", "food", "point_of_interest", "establishment"], "url": "https://maps.google.com/?cid=18180988648453574588", "user_ratings_total": 247, "utc_offset": 120, "vicinity": "Yelyzavety Chavdar Street, 18, Kyiv", "website": "http://www.sushi-point.com.ua/"}, "status": "OK"}