{"html_attributions": [], "result": {"address_components": [{"long_name": "23", "short_name": "23", "types": ["street_number"]}, {"long_name": "Bohdana Khmel'nyts'koho Street", "short_name": "Bohdana Khmel'nyts'koho St", "types": ["route"]}, {"long_name": "Shevchenkivs'kyi district", "short_name": "Shevchenkivs'kyi district", "types": ["sublocality_level_1", "sublocality", "political"]}, {"long_name": "Kyiv", "short_name": "Kyiv", "types": ["locality", "political"]}, {"long_name": "Kyiv City", "short_name": "Kyiv City", "types": ["administrative_area_level_2", "political"]}, {"long_name": "Kyiv", "short_name": "Kyiv", "types": ["administrative_area_level_1", "political"]}, {"long_name": "Ukraine", "short_name": "UA", "types": ["country", "political"]}, {"long_name": "01030", "short_name": "01030", "types": ["postal_code"]}], "adr_address": "<span class=\"street-address\">Bohdana Khmel&#39;nyts&#39;koho St, 23</span>, <span class=\"locality\">Kyiv</span>, <span class=\"country-name\">Ukraine</span>, <span class=\"postal-code\">01030</span>", "business_status": "OPERATIONAL", "current_opening_hours": {"open_now": true, "periods": [{"close": {"date": "2024-03-17", "day": 0, "time": "2300"}, "open": {"date": "2024-03-17", "day": 0, "time": "1000"}}, {"close": {"date": "2024-03-18", "day": 1, "time": "2300"}, "open": {"date": "2024-03-18", "day": 1, "time": "0900"}}, {"close": {"date": "2024-03-19", "day": 2, "time": "2300"}, "open": {"date": "2024-03-19", "day": 2, "time": "0900"}}, {"close": {"date": "2024-03-20", "day": 3, "time": "2300"}, "open": {"date": "2024-03-20", "day": 3, "time": "0900"}}, {"close": {"date": "2024-03-21", "day": 4, "time": "2300"}, "open": {"date": "2024-03-21", "day": 4, "time": "0900"}}, {"close": {"date": "2024-03-22", "day": 5, "time": "2300"}, "open": {"date": "2024-03-22", "day": 5, "time": "0900"}}, {"close": {"date": "2024-03-23", "day": 6, "time": "2300"}, "open": {"date": "2024-03-23", "day": 6, "time": "1000"}}], "weekday_text": ["Monday: 9:00 AM – 11:00 PM", "Tuesday: 9:00 AM – 11:00 PM", "Wednesday: 9:00 AM – 11:00 PM", "Thursday: 9:00 AM – 11:00 PM", "Friday: 9:00 AM – 11:00 PM", "Saturday: 10:00 AM – 11:00 PM", "Sunday: 10:00 AM – 11:00 PM"]}, "delivery": true, "dine_in": true, "editorial_summary": {"language": "en", "overview": "Sophisticated French restaurant with a terrace offering breakfast, fine dining & wine."}, "formatted_address": "Bohdana Khmel'nyts'koho St, 23, Kyiv, Ukraine, 01030", "formatted_phone_number": "067 217 1420", "geometry": {"location": {"lat": 50.446057, "lng": 30.5115394}, "viewport": {"northeast": {"lat": 50.44750998029149, "lng": 30.5129304802915}, "southwest": {"lat": 50.4448120197085, "lng": 30.5102325197085}}}, "icon": "https://maps.gstatic.com/mapfiles/place_api/icons/v1/png_71/restaurant-71.png", "icon_background_color": "#FF9E67", "icon_mask_base_uri": "https://maps.gstatic.com/mapfiles/place_api/icons/v2/restaurant_pinlet", "international_phone_number": "+380 67 217 1420", "name": "Citronelle", "opening_hours": {"open_now": true, "periods": [{"close": {"day": 0, "time": "2300"}, "open": {"day": 0, "time": "1000"}}, {"close": {"day": 1, "time": "2300"}, "open": {"day": 1, "time": "0900"}}, {"close": {"day": 2, "time": "2300"}, "open": {"day": 2, "time": "0900"}}, {"close": {"day": 3, "time": "2300"}, "open": {"day": 3, "time": "0900"}}, {"close": {"day": 4, "time": "2300"}, "open": {"day": 4, "time": "0900"}}, {"close": {"day": 5, "time": "2300"}, "open": {"day": 5, "time": "0900"}}, {"close": {"day": 6, "time": "2300"}, "open": {"day": 6, "time": "1000"}}], "weekday_text": ["Monday: 9:00 AM – 11:00 PM", "Tuesday: 9:00 AM – 11:00 PM", "Wednesday: 9:00 AM – 11:00 PM", "Thursday: 9:00 AM – 11:00 PM", "Friday: 9:00 AM – 11:00 PM", "Saturday: 10:00 AM – 11:00 PM", "Sunday: 10:00 AM – 11:00 PM"]}, "photos": [{"height": 3024, "html_attributions": ["<a href=\"https://maps.google.com/maps/contrib/114963005392644985566\">Marianna G.</a>"], "photo_reference": "ATplDJaIi3C8ko4U2kzSmpM9Zaj3Ngmu62LJ2gsB-Q0nGya2OGyuvWUqn53KxIF6YEiV5dpk_Dmdekeb8KI2XJUinBolbE-VliZZZnRtSbfq6N1vNcoieI-gXfpEdaZ8nksBrBWBJVAP-yxl4yq22nESdrGEnFcHed1tNab4sZ1eHp8bX7l1", "width": 4032}, {"height": 6465, "html_attributions": ["<a href=\"https://maps.google.com/maps/contrib/107186502391004340270\">Citronelle</a>"], "photo_reference": "ATplDJZIlb3nglNh6sksoqGuOWqIdH82fdbaq8zIh0A2K6GY3TS12jyRUCf4GYluMEWGRnNKFWSBbFaCH1UYLV2loRiLOr3ril4nVIt04M4ptHXjCSD7NB9zun5WatCSjQIP-9Q8K5EOEXv0TRCUAVCNjiVtHUFpUinPs5rhGguBm_IGMuKE", "width": 4310}, {"height": 712, "html_attributions": ["<a href=\"https://maps.google.com/maps/contrib/107186502391004340270\">Citronelle</a>"], "photo_reference": "ATplDJZBJrRwq9SgkTDUWm_4SrqUxcsOEAuB3EPbf-b6TUWaavW3OQ9IMP9UGO8RUGsJUiLkmhq8GSsiVYw56h7IIopAgMY-D5TLddOIaW8Qnesjn6yDsqCdKZx2ql_MbgINu4NzZ2dmUj9PwMsUIYz_KFnZBBPr1-QE9gLwH7DzNIdeZYWG", "width": 960}, {"height": 3000, "html_attributions": ["<a href=\"https://maps.google.com/maps/contrib/115258394748762030172\">Сергій Лупирь</a>"], "photo_reference": "ATplDJa2d1QNpeM3hrgY03UETN-HbL_8-pPyskmHWlUWI1fVyCfMLNLQlOM96-h8tH7BVnZTU0F_NrLy6Skc8VoVyO81yg9dS7rtarRqDALuLfKsArE1ZRvghpSGxzf0YQIwqfImBULlRUpXB4s320XcnPKWI71MnKPp9stbhLHB8pQ6ECSP", "width": 4000}, {"height": 2801, "html_attributions": ["<a href=\"https://maps.google.com/maps/contrib/107953874402358602933\">Evgeniiya</a>"], "photo_reference": "ATplDJahLmVP8deIfQ_EA-UIR5B_IvDTgbtCO67nZvfCKmSCJV8oPHhKn-USZQtCR7gHEUo1N9dLWfx2h5-bqCEpr64tnyCl6P2yT1FMntgj3eG7-w-pJ0UvPz602jQ-BkXKDzbspG73ID-Jq-tzyFZDm3HWrabi8ZxtZYh9zr3mlSU3rzSv", "width": 3533}, {"height": 3910, "html_attributions": ["<a href=\"https://maps.google.com/maps/contrib/105366208804787089248\">Oleg FonAnykey</a>"], "photo_reference": "ATplDJZty-LvN36UNuXar8qb-yQ0NA9YCmT17tbPGeL25dy3ez-QxgjZI2_GFb6XfCgNQkBmyvQjCYG-mz6feHfCkQcX0lcZpa5q8DTFYcjgGBImvj5M-jqRrrPlcQZrnT1izkKnT4cdmLoD-QMEkRl9RqgeHrzN2j7Qm1RmeglGlSIT8njd", "width": 2828}, {"height": 1200, "html_attributions": ["<a href=\"https://maps.google.com/maps/contrib/107186502391004340270\">Citronelle</a>"], "photo_reference": "ATplDJa9xITblrA8mKjDf8qvHyE3yf_3o_kkt1pjy5oBCdh8CkSXnINfkyY4-a9Uf-WYq6qNg9TKr9ehWLcibFY0hu8zmmn574IX63hM93rBrWToxO5gBDlWATa2V98G5CU_2lxoBkeIswFFjRgS-TruNejx2mjqcvLatbgiqmvtQNV4UWrJ", "width": 1804}, {"height": 1200, "html_attributions": ["<a href=\"https://maps.google.com/maps/contrib/107186502391004340270\">Citronelle</a>"], "photo_reference": "ATplDJZwsjR3vOEgirKdPO0CA9kfAql3dlpS81yDyqEpUtJu9aopNyUv6x9xqJx4DoLP-xXYGO6WbL_aww7R13wRZE1DPXmWqssySP1jSTKFpoXq2yKag3lnLqQHTqmoMGXKDaDktt3-nTnNvfuREW2GmOAh7vGZI38xQjKKamoyOEUFqtw6", "width": 1800}, {"height": 4000, "html_attributions": ["<a href=\"https://maps.google.com/maps/contrib/115258394748762030172\">Сергій Лупирь</a>"], "photo_reference": "ATplDJYWwPeEJqIZAJW2qZAWi8PB8ddi7jHefhnLWRK0c72W3PVeejIDf7aRlLKny5yudqGdYr4uBoyU7eQjmPTOvbsn4omx6O7znDnG33UIwiugRHx2AgjfM1oe3eHxsuHS0pSOqIcf5OdiYRY33ICZ0qmUiJEP2baKVXO8aP5m5IpwSg-N", "width": 3000}, {"height": 3205, "html_attributions": ["<a href=\"https://maps.google.com/maps/contrib/107186502391004340270\">Citronelle</a>"], "photo_reference": "ATplDJbrgxk_JmNRI03gpj1cSbV_J1qg9J3m7LPHrkP06p3O76wuSR4IxjfGEvGf4BTxNLZVfY_0FMy-l5ILdOqE863gajzlgKdyihN8pXEy-w6BdriKWg1XqRVoCvMZwlrNmKd7ql2Ly_jF-3yD6kgzKnmBDMdU_6Vy7t1Acd3ezCpUYsk5", "width": 4807}], "place_id": "ChIJ95ClDVjO1EARZxFUI5Yi5lo", "plus_code": {"compound_code": "CGW6+CJ Kyiv, Kyiv city, Ukraine", "global_code": "9G2GCGW6+CJ"}, "price_level": 3, "rating": 4.6, "reservable": true, "reviews": [{"author_name": "Iryna Mandryka", "author_url": "https://www.google.com/maps/contrib/112468069872364005095/reviews", "language": "en", "original_language": "en", "profile_photo_url": "https://lh3.googleusercontent.com/a/ACg8ocIWpXqF8To2KaU0ISt4gtJMBaGwLzf5iEmcfCiCiXrg=s128-c0x00000000-cc-rp-mo-ba3", "rating": 5, "relative_time_description": "4 years ago", "text": "Great restaurant with calm, relaxing atmosphere for families and friends’ dinners. Amazing kitchen, awesome breakfasts with big choice. The only problem in this area is parking. But it’s not quality or dishes related to restaurant. Not chip but for fear price. Friendly staff, helpful and smiling. Clean is everywhere. Deserts are very tasty and light which is very important if you want to try everything", "time": 1554053572, "translated": false}, {"author_name": "Marianna G.", "author_url": "https://www.google.com/maps/contrib/114963005392644985566/reviews", "language": "en", "original_language": "en", "profile_photo_url": "https://lh3.googleusercontent.com/a-/ALV-UjUHRrU-j_wTpMzfSFZ0KKXPDdGo2mRG7Os1ljpSKn2v4w=s128-c0x00000000-cc-rp-mo-ba4", "rating": 5, "relative_time_description": "2 years ago", "text": "The experience is awesome from the entrance to the smallest detail. The dishes are not something extraordinary and maybe overpriced but you should really come there for absolutely incredible interior. The location nearby Opera Theatre makes it the most suitable place to have a beautiful time before or after a show.", "time": 1635029821, "translated": false}, {"author_name": "Jolee E.", "author_url": "https://www.google.com/maps/contrib/106603542755202332740/reviews", "language": "en", "original_language": "en", "profile_photo_url": "https://lh3.googleusercontent.com/a-/ALV-UjVVqRHx7VPUysJAzBrUTZULD4UbNEZXWcNpKpj54U4357IG=s128-c0x00000000-cc-rp-mo-ba5", "rating": 5, "relative_time_description": "6 years ago", "text": "Wonderful place to come in from the cold. We tried several desserts late in the evening, and the waiter was very kind and attentive to us. We sat in the downstairs room, which is richly decorated and beautifully lit at night— the pictures of the interior on Google don’t quite match the elegance in person. The Kiev Cake is delightful, as was our creme brûlée (which was lit in front of us!). The prices are high for Kiev, but so worth it :)\n\nEdit: I do not think this is a good place for kids. It’s an expensive upscale restaurant, which means they will be courteous of your family, but you in turn should be courteous of other patrons", "time": 1519981034, "translated": false}, {"author_name": "Marin LC", "author_url": "https://www.google.com/maps/contrib/102448067285203494379/reviews", "language": "en", "original_language": "en", "profile_photo_url": "https://lh3.googleusercontent.com/a-/ALV-UjUQVS2L08oZ6H2l4ZXH9nrAeqkbRXlO0EsXZj1linLfFDE=s128-c0x00000000-cc-rp-mo-ba7", "rating": 5, "relative_time_description": "4 years ago", "text": "Cosy french restaurant ideal for business lunch even breakfast. Nice deco and service. Beautiful Benedict's and Avocado toast.", "time": 1555766154, "translated": false}, {"author_name": "Marianna Aronov", "author_url": "https://www.google.com/maps/contrib/112068369752097174415/reviews", "language": "en", "original_language": "en", "profile_photo_url": "https://lh3.googleusercontent.com/a-/ALV-UjV8d9qsiBJkoDcem696XzJ4NSWgAs6yA6R-JQxznhYZlbBe=s128-c0x00000000-cc-rp-mo", "rating": 5, "relative_time_description": "2 years ago", "text": "Very nice restaurant, delicious dishes, good service, great location.", "time": 1637397774, "translated": false}], "serves_beer": true, "serves_breakfast": true, "serves_brunch": true, "serves_dinner": true, "serves_lunch": true, "serves_vegetarian_food": true, "serves_wine": true, "takeout": true, "types": ["restaurant", "food", "point_of_interest", "establishment"], "url": "https://maps.google.com/?cid=6549960736290115943", "user_ratings_total": 721, "utc_offset": 120, "vicinity": "Bohdana Khmel'nyts'koho Street, 23, Kyiv", "website": "http://citronelle.com.ua/", "wheelchair_accessible_entrance": false}, "status": "OK"}