{"html_attributions": [], "result": {"address_components": [{"long_name": "2а", "short_name": "2а", "types": ["street_number"]}, {"long_name": "Bratstva Tarasivtsiv street", "short_name": "Bratstva Tarasivtsiv St", "types": ["route"]}, {"long_name": "Darnyts'kyi District", "short_name": "Darnyts'kyi District", "types": ["sublocality_level_1", "sublocality", "political"]}, {"long_name": "Kyiv", "short_name": "Kyiv", "types": ["locality", "political"]}, {"long_name": "Kyiv City", "short_name": "Kyiv City", "types": ["administrative_area_level_2", "political"]}, {"long_name": "Kyiv", "short_name": "Kyiv", "types": ["administrative_area_level_1", "political"]}, {"long_name": "Ukraine", "short_name": "UA", "types": ["country", "political"]}, {"long_name": "02000", "short_name": "02000", "types": ["postal_code"]}], "adr_address": "<span class=\"street-address\">Bratstva Tarasivtsiv St, 2а</span>, <span class=\"locality\">Kyiv</span>, <span class=\"country-name\">Ukraine</span>, <span class=\"postal-code\">02000</span>", "business_status": "OPERATIONAL", "current_opening_hours": {"open_now": false, "periods": [{"close": {"date": "2024-03-17", "day": 0, "time": "0600"}, "open": {"date": "2024-03-17", "day": 0, "time": "0000", "truncated": true}}, {"close": {"date": "2024-03-18", "day": 1, "time": "0600"}, "open": {"date": "2024-03-17", "day": 0, "time": "1600"}}, {"close": {"date": "2024-03-19", "day": 2, "time": "0600"}, "open": {"date": "2024-03-18", "day": 1, "time": "1600"}}, {"close": {"date": "2024-03-20", "day": 3, "time": "0600"}, "open": {"date": "2024-03-19", "day": 2, "time": "1600"}}, {"close": {"date": "2024-03-21", "day": 4, "time": "0600"}, "open": {"date": "2024-03-20", "day": 3, "time": "1600"}}, {"close": {"date": "2024-03-22", "day": 5, "time": "0600"}, "open": {"date": "2024-03-21", "day": 4, "time": "1600"}}, {"close": {"date": "2024-03-23", "day": 6, "time": "0600"}, "open": {"date": "2024-03-22", "day": 5, "time": "1600"}}, {"close": {"date": "2024-03-23", "day": 6, "time": "2359", "truncated": true}, "open": {"date": "2024-03-23", "day": 6, "time": "1600"}}], "weekday_text": ["Monday: 4:00 PM – 6:00 AM", "Tuesday: 4:00 PM – 6:00 AM", "Wednesday: 4:00 PM – 6:00 AM", "Thursday: 4:00 PM – 6:00 AM", "Friday: 4:00 PM – 6:00 AM", "Saturday: 4:00 PM – 6:00 AM", "Sunday: 4:00 PM – 6:00 AM"]}, "dine_in": true, "formatted_address": "Bratstva Tarasivtsiv St, 2а, Kyiv, Ukraine, 02000", "formatted_phone_number": "097 275 2727", "geometry": {"location": {"lat": 50.40749739999999, "lng": 30.6558609}, "viewport": {"northeast": {"lat": 50.4088087802915, "lng": 30.6573935802915}, "southwest": {"lat": 50.4061108197085, "lng": 30.6546956197085}}}, "icon": "https://maps.gstatic.com/mapfiles/place_api/icons/v1/png_71/bar-71.png", "icon_background_color": "#FF9E67", "icon_mask_base_uri": "https://maps.gstatic.com/mapfiles/place_api/icons/v2/bar_pinlet", "international_phone_number": "+380 97 275 2727", "name": "Prosto Bar", "opening_hours": {"open_now": false, "periods": [{"close": {"day": 1, "time": "0600"}, "open": {"day": 0, "time": "1600"}}, {"close": {"day": 2, "time": "0600"}, "open": {"day": 1, "time": "1600"}}, {"close": {"day": 3, "time": "0600"}, "open": {"day": 2, "time": "1600"}}, {"close": {"day": 4, "time": "0600"}, "open": {"day": 3, "time": "1600"}}, {"close": {"day": 5, "time": "0600"}, "open": {"day": 4, "time": "1600"}}, {"close": {"day": 6, "time": "0600"}, "open": {"day": 5, "time": "1600"}}, {"close": {"day": 0, "time": "0600"}, "open": {"day": 6, "time": "1600"}}], "weekday_text": ["Monday: 4:00 PM – 6:00 AM", "Tuesday: 4:00 PM – 6:00 AM", "Wednesday: 4:00 PM – 6:00 AM", "Thursday: 4:00 PM – 6:00 AM", "Friday: 4:00 PM – 6:00 AM", "Saturday: 4:00 PM – 6:00 AM", "Sunday: 4:00 PM – 6:00 AM"]}, "photos": [{"height": 3120, "html_attributions": ["<a href=\"https://maps.google.com/maps/contrib/103096250412788585070\">Dmytro Fedotov</a>"], "photo_reference": "ATplDJYeq4aWbtQXiyhYODEKmdubAvhXrnxn76P5o_rm4iH0eHghuS21lZV2lTsuawdwyeYT9Du1yZQw1dUaPT3QQx3wlY2LE3BDR6ZvhTODLd07VcPyTHflHSmaN5CsMN7hPrJgW95ghgXefoWOcKcOjqSjoAHiVEsqMWLAAHh9nsY0TwMd", "width": 4160}, {"height": 5504, "html_attributions": ["<a href=\"https://maps.google.com/maps/contrib/107699891440752416520\">Yuriy Maksyom</a>"], "photo_reference": "ATplDJYMXblJv4bUyWVKUbxLYPawCVXNozgUIxNnOSg99W2pp7icIHRRC8wIrLAKRjuPs6uo95YxYx7AQcP3--35CgXdCvnytnC6vMrppt7hs2PpSQ9NpmzgYWIJEMvHzabKdiKBVYSGTBUTjQKIOp8UGrZpAnk6blOogSpsbt8R4D_LSoVI", "width": 3096}, {"height": 4032, "html_attributions": ["<a href=\"https://maps.google.com/maps/contrib/115928531849389034735\">макс колко</a>"], "photo_reference": "ATplDJZ28Adi7wtqKWV_x9_c0jKf29mT__FkB-eOwRzj8-rtjZaifLmnDCwOEEvqZIRQIADAxFtjB23afwyVAGyEmm_1teamagjH6hA_tO74lZ5R9ZJRV35Oyc3nBf0xwTupj2nueQ5re4gjhLT8ZsgRGn3PsrBZZD1DqrQvDYq3OgG-dOAN", "width": 3024}, {"height": 2592, "html_attributions": ["<a href=\"https://maps.google.com/maps/contrib/100798285438652916638\">Vit Protsenko</a>"], "photo_reference": "ATplDJZTKPFq1cQrGyNq8nIPkPXmMxXUgYfpesfjw0ZfqOlDlcgXwKnWDt9o54XABmWH8sFvMeyPvYMZc34fEtWkODw0NFm2mydJc1ns2RFt9iFQv5KtcW2230Tsx5q3kWkBbjIAUCyT5JIoyA94ZD54eOcI84cCrpBdIrstbAKuVDjMZcbV", "width": 4608}, {"height": 4032, "html_attributions": ["<a href=\"https://maps.google.com/maps/contrib/106591372363674534284\">Андрій Корзаченко</a>"], "photo_reference": "ATplDJY0BzwQwU2LKL6Z0kWYNAMQb0rW_SxvxPUVD2JBrL8FOLkyvu56Z6l3ceCgBxvkv_RrQ2mLAh33DUx_FaC-MQ0bF6A2Tj3-7nozax4NSnUSjD4OYrVgTLIgAHCX9WpAWtJVjWajUuvgaSkzKjbAIZ-jkflUrowYrlpXvoO6ACFdrrA", "width": 3024}, {"height": 4000, "html_attributions": ["<a href=\"https://maps.google.com/maps/contrib/112321538952219000015\">Victoria S</a>"], "photo_reference": "ATplDJbeDtaPHyIeLh7_L6_Yvj4vDowe2-37UCM0ONIRCE5jeSwbiU3IXFQ7SLxAKBeuvtFr9JEn7OHswObugG9ERUZlcYSYJPSATpuZWNkMahFQPSl0RqiAGmJymRdxIsMuCVAQ5st96O2ADxHaN0X0pms0oNPE8FJG6nuOUIkCGnucwt1d", "width": 1846}, {"height": 4608, "html_attributions": ["<a href=\"https://maps.google.com/maps/contrib/118364208472244384026\">Evgen Bodnar</a>"], "photo_reference": "ATplDJbMiNojyui7GAqsUs5JL4V8hTmvhz5DqETSXlxAH_7qSTeCckFSrNwibpBDbDaMpJzKGHdagybaoVGLs7WMy7naJ_HGYJv__oRlH5WB9mXSuasnq2oXnugJ8uKuV6PCWsGH1ipKcDZq7EdppUyv82z442a98u1YenLJQ4I32bv0gvSD", "width": 3456}, {"height": 3024, "html_attributions": ["<a href=\"https://maps.google.com/maps/contrib/112114490964684284195\">Віктор Пігарєв</a>"], "photo_reference": "ATplDJYnrZPbbKVDSUTXPi4oQmEQFGqfU4gXFMJEEectnm2BQwPjDNggk6IM_PmMfGKC2RFRzb7IjtVF5j00xFDjYZ7mJB4QRrCzq4mfvmWdN33sozVneI6lYkWMAF5NikIl1xoTZJdS7F7Ghwlu_qKH_lLzRSFna5Neqqj7LcTw6ChrtilA", "width": 4032}, {"height": 3000, "html_attributions": ["<a href=\"https://maps.google.com/maps/contrib/105433003522729865118\">Дмитрий Назин</a>"], "photo_reference": "ATplDJaHG8YqUqRznjdLj3Sh2ad4PPoTvuvCf0gVE1VNXuXoVhufy6E11r_yGXfQWt6ZWPaxejb3IY8SHl-R-VeGq6xv1mcUJ9nrCJGjLDH4mMqvThk2YwxhOGn1w-3arE_MdaP4A4qobZPNa7eQ9wGBd9HRAS2CcSwm9CwHMJtjHMNHAsDV", "width": 4000}, {"height": 1600, "html_attributions": ["<a href=\"https://maps.google.com/maps/contrib/108139899598957443805\">Vladymyr</a>"], "photo_reference": "ATplDJYXrKylrsy2YM3eDBRbrqnKJUCA7VHPPDqWgzb6Ye5g2BocaMSyeswA1eooL9zzcerF1vTo0f2Wf1fBYi1NgnHKLqG4RqPxM9XBu0rhqcoXtzLVHIkQdDLmDr8n-uCbpEWkHbFx1l8xHVNa-zgYVduf6lF9FuL2hvAuHkdOamUAR66Z", "width": 2400}], "place_id": "ChIJoww5V6jF1EARJGkgDDSpX7A", "plus_code": {"compound_code": "CM44+X8 Kyiv, Kyiv city, Ukraine", "global_code": "9G2GCM44+X8"}, "price_level": 2, "rating": 4.4, "reservable": true, "reviews": [{"author_name": "Victoria S", "author_url": "https://www.google.com/maps/contrib/112321538952219000015/reviews", "language": "en", "original_language": "en", "profile_photo_url": "https://lh3.googleusercontent.com/a-/ALV-UjWjFlacfFgG7_dvAuPTScEAwqyqzlr2-dq3OHOoi6qDy9M=s128-c0x00000000-cc-rp-mo-ba5", "rating": 5, "relative_time_description": "2 years ago", "text": "Good service👍", "time": 1616086251, "translated": false}, {"author_name": "Артем Матвієнко", "author_url": "https://www.google.com/maps/contrib/110848352412703099178/reviews", "language": "en", "original_language": "en", "profile_photo_url": "https://lh3.googleusercontent.com/a/ACg8ocJQidATXDBol34ABlY7nldIGPUq5G-HmwUJ3oHn-Wtx=s128-c0x00000000-cc-rp-mo", "rating": 5, "relative_time_description": "4 years ago", "text": "Nice place!", "time": 1575573827, "translated": false}, {"author_name": "Anatoliy Rybalchenko", "author_url": "https://www.google.com/maps/contrib/105150868052048206988/reviews", "language": "en", "original_language": "en", "profile_photo_url": "https://lh3.googleusercontent.com/a/ACg8ocJeXvstdshZWaN1yYxgfBogW1ENUNuT22zarMW3tdRv=s128-c0x00000000-cc-rp-mo-ba4", "rating": 5, "relative_time_description": "4 years ago", "text": "Respect!!!!", "time": 1581796874, "translated": false}, {"author_name": "Люба Васюта", "author_url": "https://www.google.com/maps/contrib/111800844934849657791/reviews", "language": "en-US", "original_language": "ru", "profile_photo_url": "https://lh3.googleusercontent.com/a-/ALV-UjWRYRJH9IAo_tMdntw7OkE5doXf8uP1aiBtSWTSOywTQdk=s128-c0x00000000-cc-rp-mo-ba3", "rating": 4, "relative_time_description": "2 years ago", "text": "Today I was with friends in this bar, it is possible to book a table, the staff is pleasant, but not inattentive, a friend ordered cheese sticks, the waiter took them to someone else’s table, I had to pull him and say that this is our order, I waited for mine for 20 minutes By the way, although the workload was 60 percent and we constantly flashed before our eyes, besides, no one clarified whether the bill was separate or joint, but perhaps it was our fault, we should have said so right away. The dishes are in a fairly budget price range, as is the alcohol. Yes, there are nuances, but not everything is so bad, so 4.", "time": 1640376008, "translated": true}, {"author_name": "Obibaz Obibaz", "author_url": "https://www.google.com/maps/contrib/104106678606673388894/reviews", "language": "en-US", "original_language": "ru", "profile_photo_url": "https://lh3.googleusercontent.com/a/ACg8ocLZiv1t6n0nZe-NhmBR7PHJrujXGgOIkgkb5qVrEjuB=s128-c0x00000000-cc-rp-mo-ba3", "rating": 5, "relative_time_description": "3 years ago", "text": "It's a great bar; I've visited it with friends many times. Nice staff. But one day, half a year ago, they brought Caesar on a plate that smelled like an old rag. For a long time the girl and I sorted out the cheese in the salad so the guys or a plate. Well, in short, everyone remained assigned an opinion)", "time": 1603748777, "translated": true}], "serves_beer": true, "serves_wine": true, "takeout": true, "types": ["bar", "point_of_interest", "establishment"], "url": "https://maps.google.com/?cid=12709062714469673252", "user_ratings_total": 381, "utc_offset": 120, "vicinity": "Bratstva Tarasivtsiv street, 2а, Kyiv", "website": "https://www.facebook.com/ProstoBarKiev/", "wheelchair_accessible_entrance": false}, "status": "OK"}