{"html_attributions": [], "result": {"address_components": [{"long_name": "6", "short_name": "6", "types": ["street_number"]}, {"long_name": "vulytsia Ivana Franka", "short_name": "vulytsia Ivana Franka", "types": ["route"]}, {"long_name": "Sofiivska Borshchahivka", "short_name": "Sofiivska Borshchahivka", "types": ["locality", "political"]}, {"long_name": "Kyjevo-Svyatoshyns'kyi district", "short_name": "Kyjevo-Svyatoshyns'kyi district", "types": ["administrative_area_level_2", "political"]}, {"long_name": "Kyivs'ka oblast", "short_name": "Kyivs'ka oblast", "types": ["administrative_area_level_1", "political"]}, {"long_name": "Ukraine", "short_name": "UA", "types": ["country", "political"]}, {"long_name": "08131", "short_name": "08131", "types": ["postal_code"]}], "adr_address": "вулиця Івана Франка, 6 Ivana Franko St, <span class=\"street-address\">vulytsia Ivana Franka, 6</span>, <span class=\"locality\">Sofiivska Borshchahivka</span>, <span class=\"region\">Kyivs&#39;ka oblast</span>, <span class=\"country-name\">Ukraine</span>, <span class=\"postal-code\">08131</span>", "business_status": "OPERATIONAL", "curbside_pickup": true, "current_opening_hours": {"open_now": true, "periods": [{"close": {"date": "2024-03-17", "day": 0, "time": "2200"}, "open": {"date": "2024-03-17", "day": 0, "time": "1100"}}, {"close": {"date": "2024-03-18", "day": 1, "time": "2200"}, "open": {"date": "2024-03-18", "day": 1, "time": "1100"}}, {"close": {"date": "2024-03-19", "day": 2, "time": "2200"}, "open": {"date": "2024-03-19", "day": 2, "time": "1100"}}, {"close": {"date": "2024-03-20", "day": 3, "time": "2200"}, "open": {"date": "2024-03-20", "day": 3, "time": "1100"}}, {"close": {"date": "2024-03-21", "day": 4, "time": "2200"}, "open": {"date": "2024-03-21", "day": 4, "time": "1100"}}, {"close": {"date": "2024-03-22", "day": 5, "time": "2200"}, "open": {"date": "2024-03-22", "day": 5, "time": "1100"}}, {"close": {"date": "2024-03-23", "day": 6, "time": "2200"}, "open": {"date": "2024-03-23", "day": 6, "time": "1100"}}], "weekday_text": ["Monday: 11:00 AM – 10:00 PM", "Tuesday: 11:00 AM – 10:00 PM", "Wednesday: 11:00 AM – 10:00 PM", "Thursday: 11:00 AM – 10:00 PM", "Friday: 11:00 AM – 10:00 PM", "Saturday: 11:00 AM – 10:00 PM", "Sunday: 11:00 AM – 10:00 PM"]}, "delivery": true, "dine_in": true, "formatted_address": "вулиця Івана Франка, 6 Ivana Franko St, vulytsia Ivana Franka, 6, Sofiivska Borshchahivka, Kyivs'ka oblast, Ukraine, 08131", "formatted_phone_number": "097 221 1901", "geometry": {"location": {"lat": 50.4000314, "lng": 30.3734607}, "viewport": {"northeast": {"lat": 50.40132688029149, "lng": 30.37491358029149}, "southwest": {"lat": 50.39862891970849, "lng": 30.3722156197085}}}, "icon": "https://maps.gstatic.com/mapfiles/place_api/icons/v1/png_71/restaurant-71.png", "icon_background_color": "#FF9E67", "icon_mask_base_uri": "https://maps.gstatic.com/mapfiles/place_api/icons/v2/restaurant_pinlet", "international_phone_number": "+380 97 221 1901", "name": "To-To", "opening_hours": {"open_now": true, "periods": [{"close": {"day": 0, "time": "2200"}, "open": {"day": 0, "time": "1100"}}, {"close": {"day": 1, "time": "2200"}, "open": {"day": 1, "time": "1100"}}, {"close": {"day": 2, "time": "2200"}, "open": {"day": 2, "time": "1100"}}, {"close": {"day": 3, "time": "2200"}, "open": {"day": 3, "time": "1100"}}, {"close": {"day": 4, "time": "2200"}, "open": {"day": 4, "time": "1100"}}, {"close": {"day": 5, "time": "2200"}, "open": {"day": 5, "time": "1100"}}, {"close": {"day": 6, "time": "2200"}, "open": {"day": 6, "time": "1100"}}], "weekday_text": ["Monday: 11:00 AM – 10:00 PM", "Tuesday: 11:00 AM – 10:00 PM", "Wednesday: 11:00 AM – 10:00 PM", "Thursday: 11:00 AM – 10:00 PM", "Friday: 11:00 AM – 10:00 PM", "Saturday: 11:00 AM – 10:00 PM", "Sunday: 11:00 AM – 10:00 PM"]}, "photos": [{"height": 3456, "html_attributions": ["<a href=\"https://maps.google.com/maps/contrib/112279842798585126364\">ТО-ТО Піца</a>"], "photo_reference": "ATplDJaP0QjT48wSzj5Y9WVUs6JC64JKxDRpPSCqaGGfcd9C94hzulziNE0Q8s0ZrwZbKO-9zyOr7Odrk1aa5uHCgXGNzmthz1igQ9R-5vy03K80OzSXaUVwMWKw0dauZLtOlLtAKb8_mDJl6TrkIc6tU0qzGJJQNBDc-jXB2qTBu9QsLkQn", "width": 3456}, {"height": 3456, "html_attributions": ["<a href=\"https://maps.google.com/maps/contrib/112279842798585126364\">ТО-ТО Піца</a>"], "photo_reference": "ATplDJYI_a8O05yNzByuPb492HIIoIbyUDjSU0XlbTeF4LRxpk6W0bvrIbtSckmhy4RtZiQZ9DFhx7GxdcqgJ2cGEVq56POuawl9Ko7lVnGk4SawpCAyV0DsKgWDPqT9ucAAj4jOCiV_soICJtA1NPyR6HoP3pIr5JiV8PCMdJ5HERQrEV0Z", "width": 5184}, {"height": 1096, "html_attributions": ["<a href=\"https://maps.google.com/maps/contrib/112279842798585126364\">ТО-ТО Піца</a>"], "photo_reference": "ATplDJYSr7MK_viM45WrZ7bxdsD9eqNrCJF7r0fCBdmyQ_RgVRQIqADzbvzJtz6A59ihnQKD_j1sqF_jS0-fWjLAy3FAoXd_m8shVPahhoVopxMORLkmIyUfmdsKXkDnFX2hUtahXYEHJE61sEN0jYBT92qGLX3yzvqSI6mSQTgiYALzR-an", "width": 1947}, {"height": 3455, "html_attributions": ["<a href=\"https://maps.google.com/maps/contrib/112279842798585126364\">ТО-ТО Піца</a>"], "photo_reference": "ATplDJYOzAfPEly1KWWJV-qntefYPYePi3UVhVeoR48x8thV2AdaqyjJLSS3PNCTEAeu66Y6Zh3EHQePK1Xb0kER7BUDW7oslT_HXgx7OcO4FQqqIzRj7g6nRwOhuoej0pVNnUGcnSpwkM-Jr6halpLQXPNGtTi7IG0X902HE23tDwVdMFlz", "width": 3455}, {"height": 2813, "html_attributions": ["<a href=\"https://maps.google.com/maps/contrib/112279842798585126364\">ТО-ТО Піца</a>"], "photo_reference": "ATplDJaDYC7eEh9o07NASVzJbviZ0asmHBoEy3d2kaUX4AAlUUE2yygMbb66ICxH_Cf6XIl4K3h8xy1409nDiuuPtMvF-LD5bBQa6zf9vSaDth2kKBeL8Ucb8CP0Znd44kNVzUyxRwGM1YGls8XEqB8Bhv8vo4QbyDakItD1Mn3EFsXX-1F9", "width": 2813}, {"height": 2448, "html_attributions": ["<a href=\"https://maps.google.com/maps/contrib/112279842798585126364\">ТО-ТО Піца</a>"], "photo_reference": "ATplDJY1FwitMZkeyFm0z9y1SQauMXnkSmuC8racZqbR_vkJzKZO3yw5kHBp6jf9oHd1-n4_06DBHvx4yFfWV8EWuNPGFE8c3YJNBGIivPLSIV0pxKakTFvwjbgabA6rpH5QLhV5dZ81K2TfcyKb1JdD09ekv82iUcePcgZ1a5SOxuPHLPqG", "width": 2448}, {"height": 3456, "html_attributions": ["<a href=\"https://maps.google.com/maps/contrib/112279842798585126364\">ТО-ТО Піца</a>"], "photo_reference": "ATplDJZrTGt3GbUBccfZMOxXwGQ4MhLjiJRB1OU_7XbOiigzwTlmveqxqJwObirD7Zu9HwD2cKhuQRt14FMFFQIsFb6E_jVFLA_WmFqDjgKe6MoDJvLhT_f9sxOY1ZTHXqXnkydL3pi4fFc9vZMLYOKSp_FIm1VA4tWQ5z3-gWIlxDcSpb-A", "width": 3456}, {"height": 3120, "html_attributions": ["<a href=\"https://maps.google.com/maps/contrib/103580915946711636502\">Юрий BAZA</a>"], "photo_reference": "ATplDJbXGvfTIBu2c2eEOuHWOMfXCCYhyb6eSM_LZzuMBzKnax2K2TEPm9hWtURgt4vE97YKsb1w6Ks2W8-5bWBzyU2NsMp1ZsXwrIWgRCxNH3bbv2oJU2ciTPi1WXP18V-PG8O6gPdg5P3oADuADGX3vsSyjRqyVKn8yJ4ebxKoH1wAnoP4", "width": 4160}, {"height": 2706, "html_attributions": ["<a href=\"https://maps.google.com/maps/contrib/112279842798585126364\">ТО-ТО Піца</a>"], "photo_reference": "ATplDJby8K7x0iyxz_8LOc5FYTHy_pti-ayUYTbkrOfoR-B-q0F8WFYN1h0hK53uWklHi7FZyEzDwKZoXpahA4Yt7Ef2cqA1co5B95qt_DVd2YJc4LDOX__UC4nhM1T3qbqynwnMTaiSb3aiOV1quIV8Ili-KN4nFLaedbn2OsAhGk8ziEmx", "width": 4062}, {"height": 1913, "html_attributions": ["<a href=\"https://maps.google.com/maps/contrib/112279842798585126364\">ТО-ТО Піца</a>"], "photo_reference": "ATplDJY8PS8zmjuE7FZXwQGoWgVbg9oqKIMIS_vEETSGCmCpZJ1aMtAZA4Y_2kcQ2QVHQlKuMJXN5XyRA1oa8PMBxkPLifumV8qXUPILJvLtf0fgXolrGe2pl17Ew6NbQCZz6bHX0z1u4l7MmGQubF282O8RqeA-PVWFfKxy2Ug2JD-EAkkw", "width": 1913}], "place_id": "ChIJ4S3DLszL1EARcp7DZsEo8PE", "plus_code": {"compound_code": "C92F+29 Sofiivska Borschahivka, Kyiv Oblast, Ukraine", "global_code": "9G2GC92F+29"}, "price_level": 2, "rating": 4.4, "reservable": true, "reviews": [{"author_name": "mohamed amine", "author_url": "https://www.google.com/maps/contrib/110352535668535609570/reviews", "language": "en", "original_language": "en", "profile_photo_url": "https://lh3.googleusercontent.com/a-/ALV-UjVhEr8lEMDEhsOmiK2IIRJJRGxOPWQFVkzanqbfZPB92T8=s128-c0x00000000-cc-rp-mo-ba4", "rating": 3, "relative_time_description": "6 years ago", "text": "Normal restaurant with good servise", "time": 1507890506, "translated": false}, {"author_name": "Anton Chernivetskyi", "author_url": "https://www.google.com/maps/contrib/114064469059776330249/reviews", "language": "en", "original_language": "en", "profile_photo_url": "https://lh3.googleusercontent.com/a-/ALV-UjVNwmoWx3sN3LDjYirm0IRAgJrY7A4Z8R66qE0hHuUf71o=s128-c0x00000000-cc-rp-mo-ba3", "rating": 5, "relative_time_description": "3 years ago", "text": "Amazing pizza and democratic prices", "time": 1592125969, "translated": false}, {"author_name": "michael berard", "author_url": "https://www.google.com/maps/contrib/111807883948805329734/reviews", "language": "en", "original_language": "en", "profile_photo_url": "https://lh3.googleusercontent.com/a-/ALV-UjWfpY5TYNrXHO9ut8TlhOWUBte4dtmSV6n8kN_l6TGi8mY=s128-c0x00000000-cc-rp-mo-ba4", "rating": 5, "relative_time_description": "6 years ago", "text": "Fine place", "time": 1516738577, "translated": false}, {"author_name": "М К", "author_url": "https://www.google.com/maps/contrib/117212497311968680682/reviews", "language": "en-US", "original_language": "ru", "profile_photo_url": "https://lh3.googleusercontent.com/a/ACg8ocKotLio6yh-agROk2VzeZhaxeuhbFFbc1eOn5zRix2L=s128-c0x00000000-cc-rp-mo-ba6", "rating": 4, "relative_time_description": "2 years ago", "text": "Italian style pizzeria design. There are several halls and a children's room, which is very convenient. The staff is polite, but there are minor shortcomings in the work. Caesar salad is not classic, but quite tasty. Fried bacon adds its own piquancy, there is a lot of sauce, the only criticism is that the croutons are too salty. The pizza tastes great, the dough is thin as I like, there is a lot of filling, there is enough sauce. We liked both pizzas we ordered. It is also very convenient that you can pack food with you.", "time": 1624306008, "translated": true}, {"author_name": "Евгения Кочелаб", "author_url": "https://www.google.com/maps/contrib/103311616426031607504/reviews", "language": "en-US", "original_language": "ru", "profile_photo_url": "https://lh3.googleusercontent.com/a-/ALV-UjWDgMJvtek4Wo_TqIPGot3ARGx0DRTPn7yUgg1u2Ij10g=s128-c0x00000000-cc-rp-mo-ba4", "rating": 5, "relative_time_description": "2 years ago", "text": "Very tasty pizza, and the Caesar salad with salmon is just the bomb!\nBeautiful presentation, cozy room. The air conditioning works great - good, quiet, cool (we were in extreme heat).\nThere is a games room for small children and arcade machines for older ones. There is a large parking lot nearby.", "time": 1624471317, "translated": true}], "secondary_opening_hours": [{"open_now": false, "periods": [{"close": {"date": "2024-03-18", "day": 1, "time": "1800"}, "open": {"date": "2024-03-18", "day": 1, "time": "1300"}}, {"close": {"date": "2024-03-19", "day": 2, "time": "1800"}, "open": {"date": "2024-03-19", "day": 2, "time": "1300"}}, {"close": {"date": "2024-03-20", "day": 3, "time": "1800"}, "open": {"date": "2024-03-20", "day": 3, "time": "1300"}}, {"close": {"date": "2024-03-21", "day": 4, "time": "1800"}, "open": {"date": "2024-03-21", "day": 4, "time": "1300"}}, {"close": {"date": "2024-03-22", "day": 5, "time": "1800"}, "open": {"date": "2024-03-22", "day": 5, "time": "1300"}}], "type": "HAPPY_HOUR", "weekday_text": ["Monday: 1:00 – 6:00 PM", "Tuesday: 1:00 – 6:00 PM", "Wednesday: 1:00 – 6:00 PM", "Thursday: 1:00 – 6:00 PM", "Friday: 1:00 – 6:00 PM", "Saturday: Closed", "Sunday: Closed"]}, {"open_now": true, "periods": [{"close": {"date": "2024-03-17", "day": 0, "time": "2130"}, "open": {"date": "2024-03-17", "day": 0, "time": "1100"}}, {"close": {"date": "2024-03-18", "day": 1, "time": "2130"}, "open": {"date": "2024-03-18", "day": 1, "time": "1300"}}, {"close": {"date": "2024-03-19", "day": 2, "time": "2130"}, "open": {"date": "2024-03-19", "day": 2, "time": "1300"}}, {"close": {"date": "2024-03-20", "day": 3, "time": "2130"}, "open": {"date": "2024-03-20", "day": 3, "time": "1300"}}, {"close": {"date": "2024-03-21", "day": 4, "time": "2130"}, "open": {"date": "2024-03-21", "day": 4, "time": "1300"}}, {"close": {"date": "2024-03-22", "day": 5, "time": "2130"}, "open": {"date": "2024-03-22", "day": 5, "time": "1300"}}, {"close": {"date": "2024-03-23", "day": 6, "time": "2130"}, "open": {"date": "2024-03-23", "day": 6, "time": "1100"}}], "type": "DELIVERY", "weekday_text": ["Monday: 1:00 – 9:30 PM", "Tuesday: 1:00 – 9:30 PM", "Wednesday: 1:00 – 9:30 PM", "Thursday: 1:00 – 9:30 PM", "Friday: 1:00 – 9:30 PM", "Saturday: 11:00 AM – 9:30 PM", "Sunday: 11:00 AM – 9:30 PM"]}, {"open_now": true, "periods": [{"close": {"date": "2024-03-17", "day": 0, "time": "2130"}, "open": {"date": "2024-03-17", "day": 0, "time": "1100"}}, {"close": {"date": "2024-03-18", "day": 1, "time": "2130"}, "open": {"date": "2024-03-18", "day": 1, "time": "1300"}}, {"close": {"date": "2024-03-19", "day": 2, "time": "2130"}, "open": {"date": "2024-03-19", "day": 2, "time": "1300"}}, {"close": {"date": "2024-03-20", "day": 3, "time": "2130"}, "open": {"date": "2024-03-20", "day": 3, "time": "1300"}}, {"close": {"date": "2024-03-21", "day": 4, "time": "2130"}, "open": {"date": "2024-03-21", "day": 4, "time": "1300"}}, {"close": {"date": "2024-03-22", "day": 5, "time": "2130"}, "open": {"date": "2024-03-22", "day": 5, "time": "1300"}}, {"close": {"date": "2024-03-23", "day": 6, "time": "2130"}, "open": {"date": "2024-03-23", "day": 6, "time": "1100"}}], "type": "TAKEOUT", "weekday_text": ["Monday: 1:00 – 9:30 PM", "Tuesday: 1:00 – 9:30 PM", "Wednesday: 1:00 – 9:30 PM", "Thursday: 1:00 – 9:30 PM", "Friday: 1:00 – 9:30 PM", "Saturday: 11:00 AM – 9:30 PM", "Sunday: 11:00 AM – 9:30 PM"]}, {"open_now": true, "periods": [{"close": {"date": "2024-03-17", "day": 0, "time": "2130"}, "open": {"date": "2024-03-17", "day": 0, "time": "1100"}}, {"close": {"date": "2024-03-18", "day": 1, "time": "2130"}, "open": {"date": "2024-03-18", "day": 1, "time": "1300"}}, {"close": {"date": "2024-03-19", "day": 2, "time": "2130"}, "open": {"date": "2024-03-19", "day": 2, "time": "1300"}}, {"close": {"date": "2024-03-20", "day": 3, "time": "2130"}, "open": {"date": "2024-03-20", "day": 3, "time": "1300"}}, {"close": {"date": "2024-03-21", "day": 4, "time": "2130"}, "open": {"date": "2024-03-21", "day": 4, "time": "1300"}}, {"close": {"date": "2024-03-22", "day": 5, "time": "2130"}, "open": {"date": "2024-03-22", "day": 5, "time": "1300"}}, {"close": {"date": "2024-03-23", "day": 6, "time": "2130"}, "open": {"date": "2024-03-23", "day": 6, "time": "1100"}}], "type": "KITCHEN", "weekday_text": ["Monday: 1:00 – 9:30 PM", "Tuesday: 1:00 – 9:30 PM", "Wednesday: 1:00 – 9:30 PM", "Thursday: 1:00 – 9:30 PM", "Friday: 1:00 – 9:30 PM", "Saturday: 11:00 AM – 9:30 PM", "Sunday: 11:00 AM – 9:30 PM"]}], "serves_beer": true, "serves_breakfast": true, "serves_dinner": true, "serves_lunch": true, "serves_vegetarian_food": true, "serves_wine": true, "takeout": true, "types": ["meal_takeaway", "restaurant", "food", "point_of_interest", "establishment"], "url": "https://maps.google.com/?cid=17433478968669085298", "user_ratings_total": 612, "utc_offset": 120, "vicinity": "вулиця Івана Франка, 6 Ivana Franko St, vulytsia Ivana Franka, 6, Sofiivska Borshchahivka", "website": "http://toto-pizza.com.ua/", "wheelchair_accessible_entrance": false}, "status": "OK"}