{"html_attributions": [], "result": {"address_components": [{"long_name": "5", "short_name": "5", "types": ["street_number"]}, {"long_name": "Sholom-Aleikhema Street", "short_name": "Sholom-Aleikhema St", "types": ["route"]}, {"long_name": "Desnyans'kyi District", "short_name": "Desnyans'kyi District", "types": ["sublocality_level_1", "sublocality", "political"]}, {"long_name": "Kyiv", "short_name": "Kyiv", "types": ["locality", "political"]}, {"long_name": "Kyiv City", "short_name": "Kyiv City", "types": ["administrative_area_level_2", "political"]}, {"long_name": "Kyiv", "short_name": "Kyiv", "types": ["administrative_area_level_1", "political"]}, {"long_name": "Ukraine", "short_name": "UA", "types": ["country", "political"]}, {"long_name": "02156", "short_name": "02156", "types": ["postal_code"]}], "adr_address": "<span class=\"street-address\">Sholom-Aleikhema St, 5</span>, <span class=\"locality\">Kyiv</span>, <span class=\"country-name\">Ukraine</span>, <span class=\"postal-code\">02156</span>", "business_status": "OPERATIONAL", "curbside_pickup": true, "current_opening_hours": {"open_now": true, "periods": [{"close": {"date": "2024-03-17", "day": 0, "time": "2100"}, "open": {"date": "2024-03-17", "day": 0, "time": "1100"}}, {"close": {"date": "2024-03-18", "day": 1, "time": "2100"}, "open": {"date": "2024-03-18", "day": 1, "time": "1100"}}, {"close": {"date": "2024-03-19", "day": 2, "time": "2100"}, "open": {"date": "2024-03-19", "day": 2, "time": "1100"}}, {"close": {"date": "2024-03-20", "day": 3, "time": "2100"}, "open": {"date": "2024-03-20", "day": 3, "time": "1100"}}, {"close": {"date": "2024-03-21", "day": 4, "time": "2100"}, "open": {"date": "2024-03-21", "day": 4, "time": "1100"}}, {"close": {"date": "2024-03-22", "day": 5, "time": "2100"}, "open": {"date": "2024-03-22", "day": 5, "time": "1100"}}, {"close": {"date": "2024-03-23", "day": 6, "time": "2100"}, "open": {"date": "2024-03-23", "day": 6, "time": "1100"}}], "weekday_text": ["Monday: 11:00 AM – 9:00 PM", "Tuesday: 11:00 AM – 9:00 PM", "Wednesday: 11:00 AM – 9:00 PM", "Thursday: 11:00 AM – 9:00 PM", "Friday: 11:00 AM – 9:00 PM", "Saturday: 11:00 AM – 9:00 PM", "Sunday: 11:00 AM – 9:00 PM"]}, "delivery": true, "formatted_address": "Sholom-Aleikhema St, 5, Kyiv, Ukraine, 02156", "formatted_phone_number": "095 058 1160", "geometry": {"location": {"lat": 50.47153879999999, "lng": 30.6276692}, "viewport": {"northeast": {"lat": 50.47277338029149, "lng": 30.6290956302915}, "southwest": {"lat": 50.47007541970849, "lng": 30.6263976697085}}}, "icon": "https://maps.gstatic.com/mapfiles/place_api/icons/v1/png_71/restaurant-71.png", "icon_background_color": "#FF9E67", "icon_mask_base_uri": "https://maps.gstatic.com/mapfiles/place_api/icons/v2/restaurant_pinlet", "international_phone_number": "+380 95 058 1160", "name": "Kunsey sushi", "opening_hours": {"open_now": true, "periods": [{"close": {"day": 0, "time": "2100"}, "open": {"day": 0, "time": "1100"}}, {"close": {"day": 1, "time": "2100"}, "open": {"day": 1, "time": "1100"}}, {"close": {"day": 2, "time": "2100"}, "open": {"day": 2, "time": "1100"}}, {"close": {"day": 3, "time": "2100"}, "open": {"day": 3, "time": "1100"}}, {"close": {"day": 4, "time": "2100"}, "open": {"day": 4, "time": "1100"}}, {"close": {"day": 5, "time": "2100"}, "open": {"day": 5, "time": "1100"}}, {"close": {"day": 6, "time": "2100"}, "open": {"day": 6, "time": "1100"}}], "weekday_text": ["Monday: 11:00 AM – 9:00 PM", "Tuesday: 11:00 AM – 9:00 PM", "Wednesday: 11:00 AM – 9:00 PM", "Thursday: 11:00 AM – 9:00 PM", "Friday: 11:00 AM – 9:00 PM", "Saturday: 11:00 AM – 9:00 PM", "Sunday: 11:00 AM – 9:00 PM"]}, "photos": [{"height": 3560, "html_attributions": ["<a href=\"https://maps.google.com/maps/contrib/115640939272551482366\">Kunsey sushi</a>"], "photo_reference": "ATplDJZGYDdFyEDnAP5XBarBqt6AsS3lB_VYT6GqZRoadqLux-yjbunIToOwps6o0K3_OA4IEazFSk4a8KUiV2LVCnzREXeu5TDsBYDELshpSf_FhK9BOO4jWUSrDxtY0v6w0M-X0GLsJy2QofKWThxCmgIFJc3JnNHBAnvc_6Y9jJfeXriY", "width": 2848}, {"height": 2801, "html_attributions": ["<a href=\"https://maps.google.com/maps/contrib/115640939272551482366\">Kunsey sushi</a>"], "photo_reference": "ATplDJYwBxuwVWB6hO6MqJvEdKutCfxh8GdH3PqzB34PIAnXNEEW1M3SZSISun3WNDRwCCFgagD0M8_YwwWp9YkXXENt4OBuRa1DP_4RF7UYyFuM7ZLr33pVnl10Do87X_oIxcTFC52iRYbY13I1Fkq-_gwA8CjxvPq0oLVtLWzXxBouY-oO", "width": 2801}, {"height": 3024, "html_attributions": ["<a href=\"https://maps.google.com/maps/contrib/105304634874891983483\">Пётр Долматов</a>"], "photo_reference": "ATplDJaHZaJtcgYwecJII2gDUWMKNjV-BC3hKAO20nu_Vp9Nr66bSi51iWvtPMLLP2ZvJhlilS238Dd6r-5x0R2-ghlgfrmvYQ8FbE0hPO54uEGuiSdTX0xUAnZYYttlXcTZ9sHxd6HuSEIord_apWq5eYV0K4VxceXBOKQZkgVjKiiA8dDU", "width": 4032}, {"height": 3024, "html_attributions": ["<a href=\"https://maps.google.com/maps/contrib/110975504296730394538\">Маргарита Широкова</a>"], "photo_reference": "ATplDJZHVjc139XO_zDk8rCeaGpIrSWuUHt6vnFjk9CXKCUYyX3h0W_ofAM-rtahcazYgJ2azwoKIH7AoT0qiCmxemqUdFenNpnMvPYRykPOx5ReAWh94aGfqcJygVkougD7fluihZj5FlM4BzdsSLNzpQrTxVWqxAhvaANZYTY2Z13xlf56", "width": 4032}, {"height": 4928, "html_attributions": ["<a href=\"https://maps.google.com/maps/contrib/115640939272551482366\">Kunsey sushi</a>"], "photo_reference": "ATplDJaqN9kgzSKFY5Gxi2R7fJ0is9mgH9OqMLTFXges_t4LnQudt6DHPf44ERhkN1yGftxV1NL6HaVg_nP0Q0oPbDMfZnEcel7lC89qi3AfBT6GxX6MIu0lINGS8tRDSBkjTce5Nwb8uJaoGjvqOR5WOKRIit8jxZRPgK_8LxdcOr_7GP6K", "width": 3264}, {"height": 4032, "html_attributions": ["<a href=\"https://maps.google.com/maps/contrib/115640939272551482366\">Kunsey sushi</a>"], "photo_reference": "ATplDJaL3IJmgMHsoqxBYUX61nBt7uUbfMgvd9JnNfJyvDHDJXQmfnGeZyLt6sK6860T7WG3MHHuBFcjSsW9eySEc8qrgH1A8eWkejidIe3JrwsTd-0jLU7LeDFYt8M-9le_-PGWUZd7HhKZz_oZwNb3c_5YSSyQ9wTItQFt9RUcPmexKFpu", "width": 3024}, {"height": 4272, "html_attributions": ["<a href=\"https://maps.google.com/maps/contrib/115640939272551482366\">Kunsey sushi</a>"], "photo_reference": "ATplDJYH12E7gvY8Ntx7gNOpmrQdAct2pCtXso6jtLNr_NoVqLf5W-1qMiTj3gIIlnnR1sgUexFKzq1ucmL7ikI4A5eBy03434lUJSl4RNTOngHts5IGCEU5TIuC6yxprIy7iOgJzW_siK99pVyXrN0wAlIT3b6gBFxZ942r8Lei1SCpZwR0", "width": 2848}, {"height": 4928, "html_attributions": ["<a href=\"https://maps.google.com/maps/contrib/115640939272551482366\">Kunsey sushi</a>"], "photo_reference": "ATplDJZChP7-tuMaF0pYcqhwd6fCql7rEsZbg1VdvReykCaAgAzjyhG_Sz7CceHdqiw9vkazXQVF1-uh5rm2_PMS85qdBfUQF2lx3ysfRwzW4zFcqMOSgFkT5JKnvT-tcAxIrIQt9pQKwmnvQC1TrcNqwgsAPehXtBT34Z69aJEWW3e_7Chq", "width": 3264}, {"height": 4928, "html_attributions": ["<a href=\"https://maps.google.com/maps/contrib/115640939272551482366\">Kunsey sushi</a>"], "photo_reference": "ATplDJalja50A4hZlMAg4mUPU4BnY-WvZ4a0NGJfZ1lc_jDvTAPEiCOHKfswehi4euWBeE5L9PVdXkrNB1qMZE7ikpUbejs2hvm46xnugzKrq1ngI2ZbIEm5YBvn0ITg533YenjSxq4hE04wTQHyhhqBr_OI3egrBLk2kd9c-XStErZLX6j1", "width": 3264}, {"height": 4800, "html_attributions": ["<a href=\"https://maps.google.com/maps/contrib/115640939272551482366\">Kunsey sushi</a>"], "photo_reference": "ATplDJYlmZtMa2vmsTJuYFG2FnzOIiPql-QNlY3AQeKKHbJqEpgGuZvRbgce7KtGroRDj97y8uE_zDqhtjT-mo3mb9BvRhA8QaSyEvy4Ckrl6Rgs19k_H9jgCbSL2o6aW8aEMZ61BSpYRcm-tT3uJDqsYYi1Vg08ByqqKUsj6IFlo_6t0QeR", "width": 3179}], "place_id": "ChIJVwoJSW3R1EARv44lsUL4vh0", "plus_code": {"compound_code": "FJCH+J3 Kyiv, Kyiv city, Ukraine", "global_code": "9G2GFJCH+J3"}, "rating": 4.8, "reservable": true, "reviews": [{"author_name": "Ars Ventus", "author_url": "https://www.google.com/maps/contrib/113002174385792231387/reviews", "language": "en-US", "original_language": "uk", "profile_photo_url": "https://lh3.googleusercontent.com/a-/ALV-UjWfmf-Bj2WGQtHmKt5ugUUuFT54mpsHvclpQRIi4Q5G5Q=s128-c0x00000000-cc-rp-mo", "rating": 3, "relative_time_description": "a month ago", "text": "In general, it is normal, the rolls are tasty. But the suspicious sticky viscous mass of poisonous green color instead of wasabi and poisonous red ginger with a sharp chemical smell really spoiled the experience.", "time": 1706554120, "translated": true}, {"author_name": "Пётр Долматов", "author_url": "https://www.google.com/maps/contrib/105304634874891983483/reviews", "language": "en-US", "original_language": "uk", "profile_photo_url": "https://lh3.googleusercontent.com/a/ACg8ocLGcfcNUP92iJyJlIH1WJBHYAu9DmzKy3yOMiB8w3au=s128-c0x00000000-cc-rp-mo", "rating": 5, "relative_time_description": "2 months ago", "text": "Thank you very much for the delicious sushi. Sorry, I'm not good at taking pictures. Sushi is very tasty. Happy New Year to you.", "time": 1704047492, "translated": true}, {"author_name": "Alexander Lenz", "author_url": "https://www.google.com/maps/contrib/111060620055474867782/reviews", "language": "en-US", "original_language": "ru", "profile_photo_url": "https://lh3.googleusercontent.com/a-/ALV-UjUwlAtalKzZ1S2bF6CPhA3k49Ydm1GHi-uwyeOvxfyZZZE=s128-c0x00000000-cc-rp-mo", "rating": 4, "relative_time_description": "2 years ago", "text": "Very questionable sushi.\nWe took the Kaisen set, there was absolutely no salmon in Philadelphia, no texture, the rest of the rolls, frankly, create a lot of questions in terms of combination, for example:\n1) roll with bacon?\n2) Hot roll, in caviar, which has no texture at all, it is rice with cheese inside, without any fastening with the same nori, for example. As a result, as soon as you start picking it up with chopsticks, it immediately divides into 2))\n3) Roll with crab sticks, absolutely dry, not to mention a very large amount of rice, which is not even evenly distributed\n4) Hot roll with cucumber... Well, if of course you like warm cucumber, then this will probably be delicious)\nIn general, this is the verdict: if you just want to eat something, without any pretensions to haute cuisine, this is it :)\n\nUpd. To the owner's response.\nRegarding my reviews of other establishments, this is my personal matter, I do not write something with the aim of defaming anyone, I am simply sharing my impressions.\nAnd in order...\nI didn’t say anything bad about the bacon roll, it’s just that it’s very unusual.\nThe hot roll with caviar really just wasn’t picked up properly with chopsticks and there was no nori there.\nWell, about the hot roll, which is with cucumber, you can see in the photo that 50% of the filling is cucumber. Which, alas, when heated does not create the most pleasant impression of the roll.\nAnd yes, this set is deliberately my choice, and a good establishment should not have such problems from the start. All the best and good luck in business ;)", "time": 1627479794, "translated": true}, {"author_name": "Ольга Форест", "author_url": "https://www.google.com/maps/contrib/103999403776947583517/reviews", "language": "en-US", "original_language": "uk", "profile_photo_url": "https://lh3.googleusercontent.com/a-/ALV-UjWzwCU0iw-HSJf6Lik4P3_AI1RhDS23rFvjTqF1UDgd=s128-c0x00000000-cc-rp-mo", "rating": 5, "relative_time_description": "8 months ago", "text": "Good day. The rolls are delicious, there is a lot of filling and thin rice, nori is not rubbery! There is a discount for self-delivery. Everything is well packaged and enough sauces\nAll families of four!! I liked the roles.", "time": 1689829009, "translated": true}, {"author_name": "Ира Хохотушка", "author_url": "https://www.google.com/maps/contrib/111853525937540497877/reviews", "language": "en-US", "original_language": "ru", "profile_photo_url": "https://lh3.googleusercontent.com/a/ACg8ocITGdv4aFy0KEURuOShXIx-3rg7NbRh8DWX5xcEFrJ-=s128-c0x00000000-cc-rp-mo-ba3", "rating": 5, "relative_time_description": "2 years ago", "text": "Good afternoon. We took it here for the first time, we were not disappointed, they gave us a 10% discount for pickup, they said it was 30 minutes and that was it. Very nice people work in a team. Well done", "time": 1637010847, "translated": true}], "serves_dinner": true, "serves_lunch": true, "takeout": true, "types": ["restaurant", "food", "point_of_interest", "establishment"], "url": "https://maps.google.com/?cid=2143423437998493375", "user_ratings_total": 115, "utc_offset": 120, "vicinity": "Sholom-Aleikhema Street, 5, Kyiv", "website": "http://kunseysushi.kiev.ua/"}, "status": "OK"}