{"html_attributions": [], "result": {"address_components": [{"long_name": "20", "short_name": "20", "types": ["street_number"]}, {"long_name": "Beresteiskyi Avenue", "short_name": "Beresteiskyi Ave", "types": ["route"]}, {"long_name": "Shevchenkivs'kyi district", "short_name": "Shevchenkivs'kyi district", "types": ["sublocality_level_1", "sublocality", "political"]}, {"long_name": "Kyiv", "short_name": "Kyiv", "types": ["locality", "political"]}, {"long_name": "Kyiv City", "short_name": "Kyiv City", "types": ["administrative_area_level_2", "political"]}, {"long_name": "Kyiv", "short_name": "Kyiv", "types": ["administrative_area_level_1", "political"]}, {"long_name": "Ukraine", "short_name": "UA", "types": ["country", "political"]}, {"long_name": "04116", "short_name": "04116", "types": ["postal_code"]}], "adr_address": "<span class=\"street-address\">Beresteiskyi Ave, 20</span>, <span class=\"locality\">Kyiv</span>, <span class=\"country-name\">Ukraine</span>, <span class=\"postal-code\">04116</span>", "business_status": "OPERATIONAL", "curbside_pickup": false, "current_opening_hours": {"open_now": true, "periods": [{"close": {"date": "2024-03-17", "day": 0, "time": "2100"}, "open": {"date": "2024-03-17", "day": 0, "time": "0830"}}, {"close": {"date": "2024-03-18", "day": 1, "time": "2100"}, "open": {"date": "2024-03-18", "day": 1, "time": "0800"}}, {"close": {"date": "2024-03-19", "day": 2, "time": "2100"}, "open": {"date": "2024-03-19", "day": 2, "time": "0800"}}, {"close": {"date": "2024-03-20", "day": 3, "time": "2100"}, "open": {"date": "2024-03-20", "day": 3, "time": "0800"}}, {"close": {"date": "2024-03-21", "day": 4, "time": "2100"}, "open": {"date": "2024-03-21", "day": 4, "time": "0800"}}, {"close": {"date": "2024-03-22", "day": 5, "time": "2100"}, "open": {"date": "2024-03-22", "day": 5, "time": "0800"}}, {"close": {"date": "2024-03-23", "day": 6, "time": "2100"}, "open": {"date": "2024-03-23", "day": 6, "time": "0830"}}], "weekday_text": ["Monday: 8:00 AM – 9:00 PM", "Tuesday: 8:00 AM – 9:00 PM", "Wednesday: 8:00 AM – 9:00 PM", "Thursday: 8:00 AM – 9:00 PM", "Friday: 8:00 AM – 9:00 PM", "Saturday: 8:30 AM – 9:00 PM", "Sunday: 8:30 AM – 9:00 PM"]}, "delivery": true, "dine_in": true, "formatted_address": "Beresteiskyi Ave, 20, Kyiv, Ukraine, 04116", "formatted_phone_number": "0800 302 877", "geometry": {"location": {"lat": 50.44994260000001, "lng": 30.4762886}, "viewport": {"northeast": {"lat": 50.45123708029151, "lng": 30.47700505000001}, "southwest": {"lat": 50.44853911970851, "lng": 30.47413924999999}}}, "icon": "https://maps.gstatic.com/mapfiles/place_api/icons/v1/png_71/cafe-71.png", "icon_background_color": "#FF9E67", "icon_mask_base_uri": "https://maps.gstatic.com/mapfiles/place_api/icons/v2/cafe_pinlet", "international_phone_number": "+380 800 302 877", "name": "Pyrizhkova Titka Klara", "opening_hours": {"open_now": true, "periods": [{"close": {"day": 0, "time": "2100"}, "open": {"day": 0, "time": "0830"}}, {"close": {"day": 1, "time": "2100"}, "open": {"day": 1, "time": "0800"}}, {"close": {"day": 2, "time": "2100"}, "open": {"day": 2, "time": "0800"}}, {"close": {"day": 3, "time": "2100"}, "open": {"day": 3, "time": "0800"}}, {"close": {"day": 4, "time": "2100"}, "open": {"day": 4, "time": "0800"}}, {"close": {"day": 5, "time": "2100"}, "open": {"day": 5, "time": "0800"}}, {"close": {"day": 6, "time": "2100"}, "open": {"day": 6, "time": "0830"}}], "weekday_text": ["Monday: 8:00 AM – 9:00 PM", "Tuesday: 8:00 AM – 9:00 PM", "Wednesday: 8:00 AM – 9:00 PM", "Thursday: 8:00 AM – 9:00 PM", "Friday: 8:00 AM – 9:00 PM", "Saturday: 8:30 AM – 9:00 PM", "Sunday: 8:30 AM – 9:00 PM"]}, "photos": [{"height": 1200, "html_attributions": ["<a href=\"https://maps.google.com/maps/contrib/106924020812044557964\">Пиріжкова Тітка Клара</a>"], "photo_reference": "ATplDJaTpIlG4zYMo2cFZuh5mBrWjgtcakLy6dnZWQcH5utVuBsrUtZlUSoOhuR1lj2zrjEpkf8gFezw6vLvL6L6XDbqwv12WHoSdiYL6dACHw-_p6W9vRmQFK6c04M8Av-tHR4vZ3ZoHt_NwB9sQnksibkrvZ69em2CBWrMExbMYXKpGEst", "width": 1600}, {"height": 790, "html_attributions": ["<a href=\"https://maps.google.com/maps/contrib/106924020812044557964\">Пиріжкова Тітка Клара</a>"], "photo_reference": "ATplDJZWFWgI7hr8hC2U2Kb0e8rW0FJQOAYARB9b71V98RlSiqxlpCCnoMRD1G9-1MQwo-GeX4Ypt5ry5QL1FnBcXcAkBdWkUcImlPD1ilNM7Qs-blH6GOFKSepeCtiJK_ou57Pc8j28dtn1S34cX-_MyMowuS1IF-f3aTiNe73Ei5eaNPMg", "width": 796}, {"height": 4096, "html_attributions": ["<a href=\"https://maps.google.com/maps/contrib/110991398172165188073\">Andrii Martynov (Karcher)</a>"], "photo_reference": "ATplDJYRxPp1sQYD1JUZjUZS3pKPuNZa3h9t0BlujP6apBDf2Xtm8SdSaaeamkwf938hVmKSd-KQlxP92QgbOf2goL_tR-SPMyE-EDgglkH53W5pQivrm9HUh5qVrghVC7Xn6nnOi9Umevl-Q3OWDj9mmf30dPu4EdpVOqitMqj7H3XfU2HR", "width": 3072}, {"height": 4032, "html_attributions": ["<a href=\"https://maps.google.com/maps/contrib/113387476707706500117\">Valeriy Radzikhovskiy</a>"], "photo_reference": "ATplDJbkFjI_-FqDkpLHE8UGRc6H6f5shUEqEbm6DoBMbWuyc1_Va6cMpiaAlSybZzEkOI776PMCWaFDc1igYAK0BsEzBuWsVh1CeS1yqpkclPqnm1mibRKTJniiTrX2gBSVt7__2uGWzFb0ikNu4sVy7Pk_zh5pibScUkYXb3JQ2f5-ybLB", "width": 3024}, {"height": 2992, "html_attributions": ["<a href=\"https://maps.google.com/maps/contrib/112662119673811113700\">Aneytis Sax Player</a>"], "photo_reference": "ATplDJaGohtgmLkueD_8OuVN_VGbwRiBlub_7fHl6FzrLci2IrKCDHZGfF0p6ktuPN1ijwEI8H1Oa117Udfkq8CRI81QX3LEyNiKHFMA6hut337lyOK0FJ0I9IXb9FjSKiwmTvwV_8_dKZNHZlFySmrAHj_x1kEOfiw_swslz52TcOStsG3y", "width": 2992}, {"height": 4032, "html_attributions": ["<a href=\"https://maps.google.com/maps/contrib/101911951529562364024\">Inness Brand</a>"], "photo_reference": "ATplDJYdPJMkUFcAcnGppkaV17qJb-J2hwk-bFc9TdmdsTOu_1qG0AxQVahGmCnA8r2TP1lPd482-ahdBUCk4YNtUHiSUq8zJTYX6w74vBnOcXAOakchImEShV_bAMo9phS2o7X-Ib9NdS9sahmCqfuOm7TKt-T3H1MROZ4mZKbRCHKlaDQ7", "width": 3024}, {"height": 1920, "html_attributions": ["<a href=\"https://maps.google.com/maps/contrib/109452657309505795066\">Вадим Шахназаров</a>"], "photo_reference": "ATplDJY7zkqCr4D3qJ5_W_vRm3reURsXh-Hai6aktUd7QVyjrXK6hfmofmywBf4IptKmRB9JZL_RimmjuD7x9eGitZu0FuQ00BRGttxq3_QOqwtYToq6CMX9k6rmfsIMLyKCAOdOXLzN6rMGMs_hd8tU4oDpbJnlIRKpxctQPz7kW9V3W2EM", "width": 1080}, {"height": 4032, "html_attributions": ["<a href=\"https://maps.google.com/maps/contrib/118095120854848344471\">Anatol Fon-Filandra</a>"], "photo_reference": "ATplDJZLdW2vRYSCa65pgFqCqvmEoPtRsatP9VdnccL8xFdcKDhBO1plAsvKuF9-t-hwngsCWrgdESFDtpy7iPIitknGz2tzn7D6jMUKgjuou1aOI5-gZhN60GQRJsIGA7pw2IHDTwKlOZoff0v-6Xw7TUCaFhbYiwmjrK3bair05StfM1bx", "width": 3024}, {"height": 4032, "html_attributions": ["<a href=\"https://maps.google.com/maps/contrib/115271697745176370213\">Слава Дихтяренко</a>"], "photo_reference": "ATplDJajFKQSsUfXEoS3ooCQmVlIArYdO2ldVpKbdEqIYo86hE_ASuig9DTYHLaIvFajTLthwNKI1MnLc_fXyRzZHcMWjW1FVctGsdq1R7Tcvw3AE7Riz4T0Yv1SsSd1mkvp5j7BKxc_7l69itSpPkPt782RcCkbdWzqm2h1EyDk__VElWQ-", "width": 3024}, {"height": 2663, "html_attributions": ["<a href=\"https://maps.google.com/maps/contrib/110991398172165188073\">Andrii Martynov (Karcher)</a>"], "photo_reference": "ATplDJZL9vmEi-DaIeYvdaCVnTocgiuPz6Z575kcku62niHQ6DY6OFqfur4txpnj8OYV49Q8JzBVXLQmR6GOybkFzTgSnZ5-4_eOjzIxeoCNJwvAvA8BHd1XcY0Od31ZPyQ1QMMkblhDru3nx4qwdMXOhNhQortlELn6pOhDCljqmKJRKMbo", "width": 1433}], "place_id": "ChIJ3_RsIz_P1EARoHpwdjVp1s8", "plus_code": {"compound_code": "CFXG+XG Kyiv, Kyiv city, Ukraine", "global_code": "9G2GCFXG+XG"}, "price_level": 1, "rating": 4.7, "reviews": [{"author_name": "Слава Дихтяренко", "author_url": "https://www.google.com/maps/contrib/115271697745176370213/reviews", "language": "en-US", "original_language": "ru", "profile_photo_url": "https://lh3.googleusercontent.com/a/ACg8ocKY_aAHO69eCS30mJgVvo_Dl92KLJA-V9wz7io2ux5m=s128-c0x00000000-cc-rp-mo-ba7", "rating": 4, "relative_time_description": "2 years ago", "text": "Pirozhkovy Aunt Klara can be found in many districts of Kyiv. I tried pies for the first time a long time ago and was surprised that they had a lot of filling. The coffee is not very good, better focus on the pies. Available with and without yeast text. Very tasty with poppy seeds and veal. We didn’t go with mushrooms, the mushrooms weren’t tasty and pies with peach, the artificial taste of peach was very noticeable.", "time": 1623512472, "translated": true}, {"author_name": "Inness Brand", "author_url": "https://www.google.com/maps/contrib/101911951529562364024/reviews", "language": "en-US", "original_language": "ru", "profile_photo_url": "https://lh3.googleusercontent.com/a-/ALV-UjWOLvPZp3qVXdSdCE8YUczcK_BR1WnzOrUyKaoyf3_4CvM=s128-c0x00000000-cc-rp-mo-ba4", "rating": 5, "relative_time_description": "2 years ago", "text": "The place is inexpensive, but still has a pretty tasty meal. There are not only pies here, there is a selection of salads and desserts, by the way, the anthill is very tasty and many people like Olivier here. Maybe because the place is quite new, it’s very clean, tidy, you can even work on your laptop with a cool view, it’s more convenient than in many cafes, because there aren’t very many people and there are comfortable tables, sockets, and wifi! I recommend!", "time": 1634309380, "translated": true}, {"author_name": "Анастасія Тітова", "author_url": "https://www.google.com/maps/contrib/116559240254733509321/reviews", "language": "en-US", "original_language": "ru", "profile_photo_url": "https://lh3.googleusercontent.com/a-/ALV-UjUP3bx7boD-5vlc_5XZYmSN67hq8x9gpqW4Fl61O8S-ntA=s128-c0x00000000-cc-rp-mo-ba5", "rating": 5, "relative_time_description": "3 years ago", "text": "Quite spacious with plenty of room to sit inside and outside. As everywhere else, these pies are delicious. At lunchtime, of course, there are no longer discounted pies.\n\nThey opened recently, and the navigator showed a strange entrance to the middle of the house. In fact, it is located on the corner closest to the city center ;) so you can turn straight to it from the avenue and park your car on the street. If there is room.", "time": 1601472720, "translated": true}, {"author_name": "Анна Пономаренко", "author_url": "https://www.google.com/maps/contrib/109134042178158399506/reviews", "language": "en-US", "original_language": "uk", "profile_photo_url": "https://lh3.googleusercontent.com/a-/ALV-UjVw_Rb89xe569w2adwT6uewj6D-BAupK0aa1AiqEgCsJQ=s128-c0x00000000-cc-rp-mo-ba3", "rating": 5, "relative_time_description": "2 years ago", "text": "Well, it's really delicious 😍😍😍 also nice and fast staff, pleasant atmosphere, and you will definitely be delighted with the prices, just like me)) I highly recommend trying their broth 🤤 you can eat at them or take it away. Highly recommend!", "time": 1631721066, "translated": true}, {"author_name": "Anatol Fon-Filandra", "author_url": "https://www.google.com/maps/contrib/118095120854848344471/reviews", "language": "en-US", "original_language": "uk", "profile_photo_url": "https://lh3.googleusercontent.com/a-/ALV-UjVWqccRMH7eb2nYMEwG4Ua2jaG2unuGDIgPacvt_Mksw3Q=s128-c0x00000000-cc-rp-mo-ba4", "rating": 5, "relative_time_description": "2 years ago", "text": "Cool here! Homemade baking. Yesterday's pastries with a discount. Many types of drinks. Well, the most important thing is the atmosphere like at your aunt's. Panoramic windows, vases, smell, chairs, light and cakes. Mmmm, deliciousness!!", "time": 1628054765, "translated": true}], "takeout": true, "types": ["cafe", "bakery", "food", "store", "point_of_interest", "establishment"], "url": "https://maps.google.com/?cid=14976273289208429216", "user_ratings_total": 160, "utc_offset": 120, "vicinity": "Beresteiskyi Avenue, 20, Kyiv", "website": "https://klara.ua/"}, "status": "OK"}